Workbook
Name RATE: '[1]Otomasi adjst'!$C$2

Sheet 2026
A1: DAFTAR RINCIAN
A2: 1. Profil Maturitas
F3: dalam Ribuan USD
A4: 46203 | B4: Aset | C4: Kewajiban | D4: Selisih | E4: Profil Maturitas | F4: Reserve Requirement | G4: Traffic Light
A5: Hongkong | B5: =HK!J6 -> 666419 | C5: =HK!J7 -> 281066 | D5: =B5-C5 -> 385353 | E5: =B5/C5 -> 2.371041 | F5: OK | G5: =IF(E5>100%,"Green",IF(E5>70%,"Yellow","Red")) -> Green | H5: = | I5: =B5-B19 -> 86914 | J5: =C5-C19 -> 34390 | M5: =E5-E19 -> 0.021785262
A6: London | B6: =LDN!J8 -> 88446 | C6: =LDN!J9 -> 64768 | D6: =B6-C6 -> 23678 | E6: =B6/C6 -> 1.3655818 | F6: OK | G6: =IF(E6>100%,"Green",IF(E6>70%,"Yellow","Red")) -> Green | H6: = | I6: =B6-B20 -> 3613 | J6: =C6-C20 -> 24043 | M6: =E6-E20 -> -0.7174876
A7: New York | B7: =NY!J9 -> 1444597.6 | C7: =NY!J8 -> 1318744.6 | D7: =B7-C7 -> 125853 | E7: =B7/C7 -> 1.0954339 | F7: OK | G7: =IF(E7>100%,"Green",IF(E7>70%,"Yellow","Red")) -> Green | H7: = | I7: =B7-B21 -> 1041978.8 | J7: =C7-C21 -> 1032114.8 | M7: =E7-E21 -> -0.30923086
A8: Seoul | B8: =SEO!K8 -> 37739 | C8: =SEO!K9 -> 2527 | D8: =B8-C8 -> 35212 | E8: =B8/C8 -> 14.934309 | F8: OK | G8: =IF(E8>100%,"Green",IF(E8>70%,"Yellow","Red")) -> Green | H8: = | I8: =B8-B22 -> 12683 | J8: =C8-C22 -> -13 | M8: =E8-E22 -> 5.0697425
A9: Singapore | B9: =SG!N8 -> 490287 | C9: =SG!N9 -> 431818 | D9: =B9-C9 -> 58469 | E9: =B9/C9 -> 1.135402 | F9: OK | G9: =IF(E9>100%,"Green",IF(E9>70%,"Yellow","Red")) -> Green | H9: = | I9: =B9-B23 -> -99751 | J9: =C9-C23 -> 71714 | M9: =E9-E23 -> -0.50311914
A10: Tokyo | B10: =TKY!J7 -> 596768 | C10: =TKY!J8 -> 476706 | D10: =B10-C10 -> 120062 | E10: =B10/C10 -> 1.2518575 | F10: OK | G10: =IF(E10>100%,"Green",IF(E10>70%,"Yellow","Red")) -> Green | H10: = | I10: =B10-B24 -> -55305 | J10: =C10-C24 -> -43622 | M10: =E10-E24 -> -0.0013385219
A15: DAFTAR RINCIAN
A16: 1. Profil Maturitas
B17: =B6-B20 -> 3613 | C17: =C6-C20 -> 24043 | F17: dalam Ribuan USD
A18: 46173 | B18: Aset | C18: Kewajiban | D18: Selisih | E18: Profil Maturitas | F18: Reserve Requirement | G18: Traffic Light
A19: Hongkong | B19: 579505 | C19: 246676 | D19: 332829 | E19: 2.3492557 | F19: OK | G19: Green
A20: London | B20: 84833 | C20: 40725 | D20: 44108 | E20: 2.0830694 | F20: OK | G20: Green
A21: New York | B21: 402618.82 | C21: 286629.82 | D21: 115989 | E21: 1.4046648 | F21: OK | G21: Green
A22: Seoul | B22: 25056 | C22: 2540 | D22: 22516 | E22: 9.8645669 | F22: OK | G22: Green
A23: Singapore | B23: 590038 | C23: 360104 | D23: 229934 | E23: 1.6385211 | F23: OK | G23: Green
A24: Tokyo | B24: 652073 | C24: 520328 | D24: 131745 | E24: 1.2531961 | F24: OK | G24: Green

Sheet upload
A1: 46203 | B1: Aset | C1: Kewajiban | D1: Selisih | E1: Profil Maturitas | F1: Reserve Requirement | G1: Traffic Light
A2: Hongkong | B2: 666419 | C2: 281066 | D2: 385353 | E2: 2.371041 | F2: OK | G2: Green
A3: London | B3: 88446 | C3: 64768 | D3: 23678 | E3: 1.3655818 | F3: OK | G3: Green
A4: New York | B4: 1444597.6 | C4: 1318744.6 | D4: 125853 | E4: 1.0954339 | F4: OK | G4: Green
A5: Seoul | B5: 37739 | C5: 2527 | D5: 35212 | E5: 14.934309 | F5: OK | G5: Green
A6: Singapore | B6: 490287 | C6: 431818 | D6: 58469 | E6: 1.135402 | F6: OK | G6: Green
A7: Tokyo | B7: 596768 | C7: 476706 | D7: 120062 | E7: 1.2518575 | F7: OK | G7: Green

Sheet Sheet3

Sheet HK
A2: A | B2: B | C2: C | D2: D | E2: E | F2: F | G2: G | J2: H | K2: I | L2: J | M2: K | N2: L | O2: M | P2: N | AA2: Q | AB2: R | AC2: S
B4: LAPORAN PROFIL MATURITAS
B5: Periode 30 Jun 2026 | J5: Periode 31 Maret 2012
B6: (All) | J6: =SUM(K31:M31)+SUM(K67:M67) -> 666419 | L6: =J6-J7 -> 385353
J7: =+SUM(K54:M54)+SUM(K78:M78) -> 281066
N8: (ekuivalen dalam ribuan USD)
B9: Pos-Pos | J9: Balance | N9: Jatuh Tempo*) | AA9: Unit in Charge | AC9: Keterangan
H10: Items | I10: Mapping | K10: s.d 1 minggu | L10: > 1 minggu s.d 2 minggu | M10: > 2 minggu s.d. 1 bulan | N10: > 1 bln s.d 3 bln | O10: > 3 bln s.d 6 bln | P10: > 6 bln s.d 12 bln | Q10: > 1 y to 2 y | R10: > 2 y to 3 y | S10: > 3 y to 4 y | T10: > 4 y to 5 y | U10: > 5 y to 7 y | V10: > 7 y to 10 y | W10: > 10 y to 15 y | X10: > 15 y to 20 y | Y10: > 20 y | Z10: AC Balance Not Included
B12: I. | C12: NERACA
B13: A. | C13: Aset
C14: 1. | D14: Kas | H14: 1. Cash on hand | I14: AC 100001 | J14: 313 | K14: 312.99943 | L14: 0 | M14: 0 | N14: 0 | O14: 0 | P14: 0 | Q14: 0 | R14: 0 | S14: 0 | T14: 0 | U14: 0 | V14: 0 | W14: 0 | X14: 0 | Y14: 0 | AA14: BAM (TRS) | AB14: NY, LDN, SGP, HKG, TKO branch | AC14: cukup jelas
C15: 2. | D15: Penempatan pada Bank Indonesia | H15: 2. Nostro & Placement in Bank Indonesia | I15: N.A. | J15: 0 | K15: 0 | L15: 0 | M15: 0 | N15: 0 | O15: 0 | P15: 0 | Q15: 0 | R15: 0 | S15: 0 | T15: 0 | U15: 0 | V15: 0 | W15: 0 | X15: 0 | Y15: 0 | AA15: BAM (TRS) | AB15: NY, LDN, SGP, HKG, TKO branch | AC15: cukup jelas
C16: 3. | D16: Penempatan pada bank lain | H16: 3. Nostro & Placement in Other Banks | I16: AC 102001DR + 102002DR + 210001DR + 110101 + 110103 | J16: 190127 | K16: 190126.52 | L16: 0 | M16: 0 | N16: 0 | O16: 0 | P16: 0 | Q16: 0 | R16: 0 | S16: 0 | T16: 0 | U16: 0 | V16: 0 | W16: 0 | X16: 0 | Y16: 0 | AA16: BAM (TRS) | AB16: NY, LDN, SGP, HKG, TKO branch | AC16: cukup jelas
C17: 4. | D17: Surat Berharga **) | H17: 4. Securities | I17: 4. Securities
D18: a. | E18: Surat berharga korporasi | H18: a. Corporate & Bank Securities
E19: 1) | F19: diperdagangkan | H19: (1) Trading | J19: 0 | K19: 0 | L19: 0 | M19: 0 | N19: 0 | O19: 0 | P19: 0 | Q19: 0 | R19: 0 | S19: 0 | T19: 0 | U19: 0 | V19: 0 | W19: 0 | X19: 0 | Y19: 0 | AA19: BAM (TRS) | AB19: NY, LDN, SGP, HKG, TKO branch | AC19: cukup jelas
E20: 2) | F20: tersedia untuk dijual | H20: (2) AFS | J20: 0 | K20: 0 | L20: 0 | M20: 0 | N20: 0 | O20: 0 | P20: 0 | Q20: 0 | R20: 0 | S20: 0 | T20: 0 | U20: 0 | V20: 0 | W20: 0 | X20: 0 | Y20: 0 | AA20: BAM (TRS) | AB20: NY, LDN, SGP, HKG, TKO branch | AC20: cukup jelas
E21: 3) | F21: dimiliki hingga jatuh tempo | H21: (3) Held-to-Maturity | I21: N.A | J21: 0 | K21: 0 | L21: 0 | M21: 0 | N21: 0 | O21: 0 | P21: 0 | AA21: BAM (TRS) | AB21: NY, LDN, SGP, HKG, TKO branch | AC21: cukup jelas
E22: 4) | F22: pinjaman yang diberikan dan piutang | H22: (4) Loans and Receviables | I22: N.A | J22: 0 | K22: 0 | L22: 0 | M22: 0 | N22: 0 | O22: 0 | P22: 0 | AA22: BAM (TRS) | AB22: NY, LDN, SGP, HKG, TKO branch | AC22: cukup jelas
D23: b. | E23: Lainnya | H23: b. Gov & Other Securities | I23: AC 115127 + 115135 + 115136 + 115183 + 115147 +115155 +115182 + 115181 + 171101 + 179105 (Gov sec only) | J23: 143063 | K23: 0 | L23: 0 | M23: 0 | N23: 0 | O23: 0 | P23: 42564.536 | Q23: 26913.556 | R23: 6504.2806 | S23: 2837.8657 | T23: 29410.866 | U23: 34832.327 | V23: 0 | W23: 0 | X23: 0 | Y23: 0 | AA23: BAM (TRS) | AB23: NY, LDN, SGP, HKG, TKO branch | AC23: Surat Berharga yang tidak dapat dimasukkan atau digolongkan ke dalam salah satu dari huruf a dan huruf b.
C24: 5. | D24: Kredit Yang Diberikan | H24: 5. Loans (Include trade finance loans) | I24: 5. Loans (Include trade finance loans) | V24: 0
D25: a. | E25: belum jatuh tempo | H25: a. Current | I25: AC 140001 + 140003 + 140005 + 140011 | J25: 1007623 | K25: 15938.591 | L25: 7532.7609 | M25: 12508.291 | N25: 7433.6434 | O25: 33930.359 | P25: 25100 | Q25: 0 | R25: 353427.21 | S25: 370071.67 | T25: 105972.16 | U25: 9250 | V25: 66457.995 | W25: 0 | X25: 0 | Y25: 0 | AA25: BAM (TRS) | AB25: NY, LDN, SGP, HKG, TKO branch | AC25: diisi sesuai jumlah kredit yang belum jatuh tempo berdasarkan kontrak
D26: b. | E26: sudah jatuh tempo ***) | H26: b. Overdue | I26: Input based on the scheduled repayment agreed by the debtors | J26: 0 | K26: 0 | L26: 0 | M26: 0 | N26: 0 | O26: 0 | P26: 0 | Q26: 0 | R26: 0 | S26: 0 | T26: 0 | U26: 0 | V26: 0 | W26: 0 | X26: 0 | Y26: 0 | Z26: 0 | AA26: BAM (TRS) | AB26: NY, LDN, SGP, HKG, TKO branch | AC26: diisi berdasarkan perkiraan diperolehnya pembayaran atas kredit yang berdasarkan kontrak sudah jatuh tempo.
C27: 6. | D27: Tagihan lainnya | H27: 6. Other Receivables | I27: 6. Other Receivables
D28: a. | E28: Tagihan atas Surat Berharga yang dibeli dengan janji dijual kembali (Reverse Repo) | H28: a. Reverse Repos | I28: N.A. | J28: 0 | K28: 0 | L28: 0 | M28: 0 | N28: 0 | O28: 0 | P28: 0 | Q28: 0 | R28: 0 | S28: 0 | T28: 0 | U28: 0 | V28: 0 | W28: 0 | X28: 0 | Y28: 0 | AA28: BAM (TRS) | AB28: NY, LDN, SGP, HKG, TKO branch | AC28: cukup jelas
D29: b. | E29: Lainnya | H29: b. Others (Bills Receivables + Cash In Transit) | I29: AC 120001 + 150004 + 100002 | J29: 426 | K29: 0 | L29: 0 | M29: 0 | N29: 0 | O29: 425.83939 | P29: 0 | Q29: 0 | R29: 0 | S29: 0 | T29: 0 | U29: 0 | V29: 0 | W29: 0 | X29: 0 | Y29: 0 | AA29: BAM (TRS) | AB29: NY, LDN, SGP, HKG, TKO branch | AC29: Tagihan lainnya yang tidak dapat dimasukkan atau digolongkan ke dalam salah satu dari huruf a.
C30: 7. | D30: Lain-lain (Account Balance not included) For reconciliation purpose | J30: 44586.671 | Z30: 44586.671 | AA30: BAM (TRS) | AB30: NY, LDN, SGP, HKG, TKO branch | AC30: Asset yang tidak dapat dimasukkan atau digolongkan ke dalam salah satu dari pos 1 s.d. 6
B31: Total Aset | J31: 1386138.7 | K31: 206378 | L31: 7533 | M31: 12508 | N31: 7434 | O31: 34356 | P31: 67665 | Q31: 26914 | R31: 359931 | S31: 372910 | T31: 135383 | U31: 44082 | V31: 66458 | W31: 0 | X31: 0 | Y31: 0 | Z31: 44587
B33: B. | C33: Kewajiban
C34: 1. | D34: Dana Pihak Ketiga | H34: 1. Customer Deposits
D35: a. | E35: Giro | H35: a. Current Accounts | I35: AC 210001(except Bank) | J35: 57262 | K35: 57261.74 | L35: 0 | M35: 0 | N35: 0 | O35: 0 | P35: 0 | Q35: 0 | R35: 0 | S35: 0 | T35: 0 | U35: 0 | V35: 0 | W35: 0 | X35: 0 | Y35: 0 | AA35: BAM (TRS) | AB35: NY, LDN, SGP, HKG, TKO branch | AC35: cukup jelas
D36: b. | E36: Tabungan | H36: b. Savings Accounts | I36: AC 210011 | J36: 25 | K36: 25.353444 | L36: 0 | M36: 0 | N36: 0 | O36: 0 | P36: 0 | Q36: 0 | R36: 0 | S36: 0 | T36: 0 | U36: 0 | V36: 0 | W36: 0 | X36: 0 | Y36: 0 | AA36: BAM (TRS) | AB36: NY, LDN, SGP, HKG, TKO branch | AC36: cukup jelas
D37: c. | E37: Simpanan Berjangka | H37: c. Time Deposits
E38: 1) | F38: Deposit on call | H38: (1) Deposit at notice | I38: N.A. | J38: 0 | K38: 0 | L38: 0 | M38: 0 | N38: 0 | O38: 0 | P38: 0 | Q38: 0 | R38: 0 | S38: 0 | T38: 0 | U38: 0 | V38: 0 | W38: 0 | X38: 0 | Y38: 0 | AA38: BAM (TRS) | AB38: NY, LDN, SGP, HKG, TKO branch | AC38: cukup jelas
E39: 2) | F39: Deposito berjangka | H39: (2) Time Deposits | I39: AC 210031 | J39: 29058 | K39: 166.94231 | L39: 7450 | M39: 3022.9096 | N39: 18371.622 | O39: 46.68597 | P39: 0 | Q39: 0 | R39: 0 | S39: 0 | T39: 0 | U39: 0 | V39: 0 | W39: 0 | X39: 0 | Y39: 0 | AA39: BAM (TRS) | AB39: NY, LDN, SGP, HKG, TKO branch | AC39: cukup jelas
E40: 3) | F40: Lainnya | H40: (3) Others | I40: N.A. | J40: 0 | K40: 0 | L40: 0 | M40: 0 | N40: 0 | O40: 0 | P40: 0 | Q40: 0 | R40: 0 | S40: 0 | T40: 0 | U40: 0 | V40: 0 | W40: 0 | X40: 0 | Y40: 0 | AA40: BAM (TRS) | AB40: NY, LDN, SGP, HKG, TKO branch | AC40: Simpanan Berjangka yang tidak dapat dimasukkan atau digolongkan ke dalam salah satu dari angka 1) dan angka 2)
C41: 2. | D41: Kewajiban kepada Bank Indonesia | H41: 2. Laibilities to Bank Indonesia | I41: AC 210001 | J41: 135 | K41: 134.86637 | L41: 0 | M41: 0 | N41: 0 | O41: 0 | P41: 0 | Q41: 0 | R41: 0 | S41: 0 | T41: 0 | U41: 0 | V41: 0 | W41: 0 | X41: 0 | Y41: 0 | AA41: BAM (TRS) | AB41: NY, LDN, SGP, HKG, TKO branch | AC41: cukup jelas
C42: 3. | D42: Kewajiban kepada bank lain | H42: 3. Laibilities to Other Banks | I42: AC 102001 CR + 210001CR + 2100006CR + 252001 + 252002 + 253001 | J42: 1255775 | K42: 92087.996 | L42: 0 | M42: 0 | N42: 0 | O42: 492000 | P42: 444825.26 | Q42: 46861.35 | R42: 0 | S42: 0 | T42: 150000 | U42: 0 | V42: 0 | W42: 0 | X42: 0 | Y42: 30000 | AA42: BAM (TRS) | AB42: NY, LDN, SGP, HKG, TKO branch | AC42: cukup jelas
C43: 4. | D43: Surat Berharga yang Diterbitkan | H43: 4. Securities Issued
D44: a. | E44: Obligasi | H44: a. Debts | I44: N.A. | J44: 0 | K44: 0 | L44: 0 | M44: 0 | N44: 0 | O44: 0 | P44: 0 | Q44: 0 | R44: 0 | S44: 0 | T44: 0 | U44: 0 | V44: 0 | W44: 0 | X44: 0 | Y44: 0 | AA44: BAM (TRS) | AB44: NY, LDN, SGP, HKG, TKO branch | AC44: cukup jelas
D45: b. | E45: Subordinasi ****) | H45: b. Subordianted debts | I45: N.A. | J45: 0 | K45: 0 | L45: 0 | M45: 0 | N45: 0 | O45: 0 | P45: 0 | Q45: 0 | R45: 0 | S45: 0 | T45: 0 | U45: 0 | V45: 0 | W45: 0 | X45: 0 | Y45: 0 | AA45: BAM (TRS) | AB45: NY, LDN, SGP, HKG, TKO branch | AC45: cukup jelas
D46: c. | E46: Lainnya | H46: c. Others | I46: N.A. | J46: 0 | K46: 0 | L46: 0 | M46: 0 | N46: 0 | O46: 0 | P46: 0 | Q46: 0 | R46: 0 | S46: 0 | T46: 0 | U46: 0 | V46: 0 | W46: 0 | X46: 0 | Y46: 0 | AA46: BAM (TRS) | AB46: NY, LDN, SGP, HKG, TKO branch
C47: 5. | D47: Pinjaman yang Diterima | H47: 5. Loans Received
D48: a. | E48: Pinjaman Subordinasi ****) | H48: a. Subordinated | I48: N.A. | J48: 0 | K48: 0 | L48: 0 | M48: 0 | N48: 0 | O48: 0 | P48: 0 | Q48: 0 | R48: 0 | S48: 0 | T48: 0 | U48: 0 | V48: 0 | W48: 0 | X48: 0 | Y48: 0 | AA48: BAM (TRS) | AB48: NY, LDN, SGP, HKG, TKO branch | AC48: Surat Berharga subordinasi yang diperhitungkan dalam KPMM dan dilaporkan di LBU pada pos Modal Pinjaman.
D49: b. | E49: Lainnya | H49: b. Others | I49: N.A. | J49: 0 | K49: 0 | L49: 0 | M49: 0 | N49: 0 | O49: 0 | P49: 0 | Q49: 0 | R49: 0 | S49: 0 | T49: 0 | U49: 0 | V49: 0 | W49: 0 | X49: 0 | Y49: 0 | AA49: BAM (TRS) | AB49: NY, LDN, SGP, HKG, TKO branch | AC49: Surat Berharga yang Diterbitkan yang tidak dapat dimasukkan atau digolongkan ke dalam salah satu dari huruf a dan huruf b.
C50: 6. | D50: Kewajiban lainnya | H50: 6. Other liabilties | I50: 6. Other liabilties
D51: a. | E51: Kewajiban atas Surat Berharga yang dijual dengan janji dibeli kembali (Repo) | H51: a. Repo | I51: N.A. | J51: 0 | K51: 0 | L51: 0 | M51: 0 | N51: 0 | O51: 0 | P51: 0 | Q51: 0 | R51: 0 | S51: 0 | T51: 0 | U51: 0 | V51: 0 | W51: 0 | X51: 0 | Y51: 0 | AA51: BAM (TRS) | AB51: NY, LDN, SGP, HKG, TKO branch | AC51: cukup jelas
D52: b. | E52: Lainnya | H52: b. Others | I52: N.A. | J52: 0 | K52: 0 | L52: 0 | M52: 0 | N52: 0 | O52: 0 | P52: 0 | Q52: 0 | R52: 0 | S52: 0 | T52: 0 | U52: 0 | V52: 0 | W52: 0 | X52: 0 | Y52: 0 | AA52: BAM (TRS) | AB52: NY, LDN, SGP, HKG, TKO branch | AC52: Kewajiban lainnya diterima lainnya yang tidak dapat dimasukkan atau digolongkan ke dalam salah satu dari huruf a.
C53: 7. | D53: Lain-lain (Account Balance not included) For reconciliation purpose | J53: 43883.671 | Z53: 43883.671 | AA53: BAM (TRS) | AB53: NY, LDN, SGP, HKG, TKO branch | AC53: Kewajiban yang tidak dapat dimasukkan atau digolongkan ke dalam salah satu dari pos 1 s.d. 6
B54: Total Kewajiban | J54: 1386138.7 | K54: 149677 | L54: 7450 | M54: 3023 | N54: 18372 | O54: 492047 | P54: 444825 | Q54: 46861 | R54: 0 | S54: 0 | T54: 150000 | U54: 0 | V54: 0 | W54: 0 | X54: 0 | Y54: 30000 | Z54: 43883.671
B56: Selisih Aset dengan Kewajiban dalam Neraca | J56: 0 | K56: 56701 | L56: 83 | M56: 9485 | N56: -10938 | O56: -457691 | P56: -377160 | Q56: -19947 | R56: 359931 | S56: 372910 | T56: -14617 | U56: 44082 | V56: 66458 | W56: 0 | X56: 0 | Y56: -30000 | Z56: 703.32949
B58: II | C58: REKENING ADMINISTRATIF | H58: ITEMS | I58: MAPPING | AC58: hanya bagian dari pos tsb yang diperkirakan akan mempengaruhi arus kas (menjadi tagihan / kewajiban)
B59: A. | C59: Tagihan Rekening Administratif
C60: 1. | D60: Komitmen | H60: 1. Commitment
D61: a. | E61: Fasilitas pinjaman yang belum ditarik | H61: a. Unused facility limit | J61: 440000 | K61: 440000 | L61: 0 | M61: 0 | N61: 0 | O61: 0 | P61: 0 | Q61: 0 | R61: 0 | S61: 0 | T61: 0 | U61: 0 | V61: 0 | W61: 0 | X61: 0 | Y61: 0 | AA61: BIN, LMC-1, LMC-2, UMN, USK, BSK, PDM, dan KCLN | AB61: NY, LDN, SGP, HKG, TKO branch | AC61: Dana TSL, fasilitas kredit dari bank lain, fasilitas dana kredit likuiditas
D62: b. | E62: Posisi pembelian spot dan derivatif yang masih berjalan | H62: b. Unsettled Trades | AA62: LIK, dan KCLN | AB62: NY, LDN, SGP, HKG, TKO branch
E63: 1) | F63: Spot | H63: 1) Spot | J63: 0 | K63: 0 | L63: 0 | M63: 0 | N63: 0 | O63: 0 | P63: 0 | Q63: 0 | R63: 0 | S63: 0 | T63: 0 | U63: 0 | V63: 0 | W63: 0 | X63: 0 | Y63: 0 | AA63: LIK, dan KCLN | AB63: NY, LDN, SGP, HKG, TKO branch
E64: 2) | F64: Derivatif | H64: 2) Derivatives | J64: 0 | K64: 0 | L64: 0 | M64: 0 | N64: 0 | O64: 0 | P64: 0 | Q64: 0 | R64: 0 | S64: 0 | T64: 0 | U64: 0 | V64: 0 | W64: 0 | X64: 0 | Y64: 0 | AA64: LIK, dan KCLN | AB64: NY, LDN, SGP, HKG, TKO branch
D65: c. | E65: Lainnya | H65: c. Others | J65: 0 | K65: 0 | L65: 0 | M65: 0 | N65: 0 | O65: 0 | P65: 0 | Q65: 0 | R65: 0 | S65: 0 | T65: 0 | U65: 0 | V65: 0 | W65: 0 | X65: 0 | Y65: 0 | AA65: - | AC65: -
C66: 2. | D66: Kontijensi *****) | H66: 2. Continegent Assets | J66: 0 | K66: 0 | L66: 0 | M66: 0 | N66: 0 | O66: 0 | P66: 0 | Q66: 0 | R66: 0 | S66: 0 | T66: 0 | U66: 0 | V66: 0 | W66: 0 | X66: 0 | Y66: 0 | AA66: INT, OPR, dan KCLN | AB66: NY, LDN, SGP, HKG, TKO branch | AC66: Stby LC yg diterima, Garansi Bank yg diterima
B67: Total Tagihan Rekening Administratif | J67: 440000 | K67: 440000 | L67: 0 | M67: 0 | N67: 0 | O67: 0 | P67: 0 | Q67: 0 | R67: 0 | S67: 0 | T67: 0 | U67: 0 | V67: 0 | W67: 0 | X67: 0 | Y67: 0
B69: B. | C69: Kewajiban Rekening Administratif
C70: 1. | D70: Komitmen | H70: 1. Commitment
D71: a. | E71: Fasilitas kredit yang belum ditarik | H71: a. Unused facility limit | J71: 145890.61 | K71: 30666.159 | L71: 0 | M71: 10000 | N71: 40964.221 | O71: 54260.226 | P71: 10000 | Q71: 0 | R71: 0 | S71: 0 | T71: 0 | U71: 0 | V71: 0 | W71: 0 | X71: 0 | Y71: 0 | AA71: BIN, LMC-1, LMC-2, UMN, USK, BSK, PDM, dan KCLN | AB71: NY, LDN, SGP, HKG, TKO branch | AC71: Fasilitas KMK, KI, K.Konsumtif (committed & uncomitted)
D72: b. | E72: Irrevocable L/C yang masih berjalan | H72: b. Irrevocable LC | J72: 82276 | K72: 4176.5165 | L72: 76072.5 | M72: 0 | N72: 2026.75 | O72: 0 | P72: 0 | Q72: 0 | R72: 0 | S72: 0 | T72: 0 | U72: 0 | V72: 0 | W72: 0 | X72: 0 | Y72: 0 | AA72: INT, dan KCLN | AB72: NY, LDN, SGP, HKG, TKO branch | AC72: LC sight, usance , LC DN sigt, dan LC DN usance
D73: c. | E73: Posisi penjualan spot dan derivatif yang masih berjalan | H73: c. Unsettled Trades | AA73: LIK, dan KCLN
E74: 1) | F74: Spot | H74: 1) Spot | J74: 0 | K74: 0 | L74: 0 | M74: 0 | N74: 0 | O74: 0 | P74: 0 | Q74: 0 | R74: 0 | S74: 0 | T74: 0 | U74: 0 | V74: 0 | W74: 0 | X74: 0 | Y74: 0 | AA74: LIK, dan KCLN | AB74: NY, LDN, SGP, HKG, TKO branch
E75: 2) | F75: Derivatif | H75: 2) Derivatives | J75: 0 | K75: 0 | L75: 0 | M75: 0 | N75: 0 | O75: 0 | P75: 0 | Q75: 0 | R75: 0 | S75: 0 | T75: 0 | U75: 0 | V75: 0 | W75: 0 | X75: 0 | Y75: 0 | AA75: LIK, dan KCLN | AB75: NY, LDN, SGP, HKG, TKO branch
D76: d. | E76: Lainnya | H76: d. Others | J76: 0 | K76: 0 | L76: 0 | M76: 0 | N76: 0 | O76: 0 | P76: 0 | Q76: 0 | R76: 0 | S76: 0 | T76: 0 | U76: 0 | V76: 0 | W76: 0 | X76: 0 | Y76: 0 | AA76: -
C77: 2. | D77: Kontijensi ******) | H77: 2. Continegent Liability | J77: 0 | K77: 0 | L77: 0 | M77: 0 | N77: 0 | O77: 0 | P77: 0 | Q77: 0 | R77: 0 | S77: 0 | T77: 0 | U77: 0 | V77: 0 | W77: 0 | X77: 0 | Y77: 0 | AA77: INT, OPR, dan KCLN | AB77: NY, LDN, SGP, HKG, TKO branch | AC77: Stby LC yg diterbitkan Garansi Bank yg diterbitkan
B78: Total Kewajiban Rekening Administratif | J78: 228167 | K78: 34843 | L78: 76073 | M78: 10000 | N78: 42991 | O78: 54260 | P78: 10000 | Q78: 0 | R78: 0 | S78: 0 | T78: 0 | U78: 0 | V78: 0 | W78: 0 | X78: 0 | Y78: 0
B80: Selisih Tagihan dan Kewajiban dalam Rekening Administratif | J80: 211833 | K80: 405157 | L80: -76073 | M80: -10000 | N80: -42991 | O80: -54260 | P80: -10000 | Q80: 0 | R80: 0 | S80: 0 | T80: 0 | U80: 0 | V80: 0 | W80: 0 | X80: 0 | Y80: 0
B82: Selisih [(IA-IB)+(IIA-IIB)] | J82: 211833 | K82: 461858 | L82: -75990 | M82: -515 | N82: -53929 | O82: -511951 | P82: -387160 | Q82: -19947 | R82: 359931 | S82: 372910 | T82: -14617 | U82: 44082 | V82: 66458 | W82: 0 | X82: 0 | Y82: -30000
B84: Selisih Kumulatif | K84: 461858 | L84: 385868 | M84: 385353 | N84: 331424 | O84: -180527 | P84: -567687 | Q84: -587634 | R84: -227703 | S84: 145207 | T84: 130590 | U84: 174672 | V84: 241130 | W84: 241130 | X84: 241130 | Y84: 211130
B87: *) | D87: Angka-angka berdasarkan jatuh tempo sesuai dengan kontrak untuk yang memiliki jatuh tempo kontraktual dan/atau estimasi dengan menggunakan berbagai asumsi untuk yang tidak memiliki jatuh tempo kontraktual
B88: **) | D88: Termasuk Surat Berharga yang dijual dengan janji dibeli kembali (Repo)
B89: ***) | D89: Diisi berdasarkan perkiraan diperoleh pembayaran atas kredit yang berdasarkan kontrak sudah jatuh tempo
B90: ****) | D90: Termasuk yang diperhitungkan dalam KPMM dan dilaporkan di LBU pada pos Modal Pinjaman
B91: *****) | D91: Yang diperkirakan akan mempengaruhi arus kas (menjadi tagihan)
B92: ******) | D92: Yang diperkirakan akan mempengaruhi arus kas (menjadi kewajiban)
B134: ¨ | C134: Pos-pos dalam maturity profile diisi sesuai pembukuan Bank Pelapor berdasarkan sisa waktu sampai dengan jatuh tempo sesuai kontrak untuk pos neraca dan rekening administratif yang memiliki jatuh tempo kontraktual dan/ atau asumsi utk pos neraca dan rekeni
B138: ¨ | C138: Yang dimasukkan dalam pos-pos neraca adalah hanya pos-pos dengan karakteristik memiliki arus kas masuk / atau arus kas keluar, sehingga tidak seluruh pos di neraca di masukkan dalam laporan ini. Contoh pos neraca yang tidak dimasukkan dalam laporan ini an
B143: ¨ | C143: Sebagai kontrol, agar sesuai dengan neraca (balance antara asset & liability --> Total Asset - Total Liability = 0 di kolom saldo (H)), maka pos-pos yang tidak dimasukkan ke dalam maturity profile tetap dimasukkan ke pos poin 7. Lainnya diletakkan di kolo

Sheet LDN
A2: A | B2: B | C2: C | D2: D | E2: E | F2: F | G2: G | I2: H | J2: I | K2: J | L2: K | M2: L | N2: M | O2: N
B3: Formulir 4.b.
B4: MATURITY PROFILE REPORT - BNI LONDON Branch
B5: CONTRACTUAL BASED
B6: 46203
B7: Valuta Asing
I8: Aset | J8: =SUM(J14:L14)+SUM(J59:L59) -> 88446 | K8: =J8-J9 -> 23678
I9: Kewajiban | J9: =SUM(J68:L68)+SUM(J34:L34) -> 64768 | L9: =I14-I34 -> 0 | W9: in Thousand USD
B10: Pos-Pos | H10: Sandi | I10: Saldo | J10: Time to Maturity *)
J11: up to 1 week | K11: > 1 week to 2 weeks | L11: > 2 weeks to 1 month | M11: > 1 month to 3 months | N11: > 3 months to 6 months | O11: > 6 months to 1 year | P11: > 1 y to 2 y | Q11: > 2 y to 3 y | R11: > 3 y to 4 y | S11: > 4 y to 5 y | T11: > 5 y to 7 y | U11: > 7 y to 10 y | V11: > 10 y to 15 y | W11: > 15 y to 20 y | X11: > 20 y
B13: I. | C13: NERACA
B14: A. | C14: Aset | H14: 10000 | I14: =ROUND(SUM(J14:X14),0) -> 1189497 | J14: =ROUND(+J15+J16+J17+J18+J25+J28+J31,0) -> 88446 | K14: =ROUND(+K15+K16+K17+K18+K25+K28+K31,0) -> 0 | L14: =ROUND(+L15+L16+L17+L18+L25+L28+L31,0) -> 0 | M14: =ROUND(+M15+M16+M17+M18+M25+M28+M31,0) -> 8822 | N14: =ROUND(+N15+N16+N17+N18+N25+N28+N31,0) -> 19868 | O14: =ROUND(+O15+O16+O17+O18+O25+O28+O31,0) -> 31717 | P14: =ROUND(+P15+P16+P17+P18+P25+P28+P31,0) -> 16131 | Q14: =ROUND(+Q15+Q16+Q17+Q18+Q25+Q28+Q31,0) -> 207724 | ... X14: =ROUND(+X15+X16+X17+X18+X25+X28+X31,0) -> 0
C15: 1. | D15: Kas | H15: 10100 | I15: =ROUND(SUM(J15:X15),0) -> 22 | J15: 21.66859
C16: 2. | D16: Penempatan pada Bank Indonesia | H16: 10200 | I16: =ROUND(SUM(J16:X16),0) -> 0 | X16: =X17*$Z$17 -> 0
C17: 3. | D17: Penempatan pada bank lain | H17: 10300 | I17: =ROUND(SUM(J17:X17),0) -> 160636 | J17: 45178.975 | K17: 0 | L17: 0 | M17: 0 | N17: 0 | O17: 0 | P17: 0 | Q17: 0 | R17: 0 | S17: 115457.38 | T17: 0 | U17: 0 | V17: 0 | W17: 0 | X17: 0
C18: 4. | D18: Surat Berharga **) | H18: 10400 | I18: =ROUND(SUM(J18:X18),0) -> 96848 | J18: =+J19+J24 -> 0 | K18: =+K19+K24 -> 0 | L18: =+L19+L24 -> 0 | M18: =+M19+M24 -> 0 | N18: =+N19+N24 -> 0 | O18: =+O19+O24 -> 3881.9415 | P18: =+P19+P24 -> 7689.7319 | Q18: =+Q19+Q24 -> 0 | ... X18: =+X19+X24 -> 0
D19: a. | E19: Surat berharga korporasi | H19: 10420 | I19: =ROUND(SUM(J19:X19),0) -> 96848 | J19: =+SUM(J20:J23) -> 0 | K19: =+SUM(K20:K23) -> 0 | L19: =+SUM(L20:L23) -> 0 | M19: =+SUM(M20:M23) -> 0 | N19: =+SUM(N20:N23) -> 0 | O19: =+SUM(O20:O23) -> 3881.9415 | P19: =+SUM(P20:P23) -> 7689.7319 | Q19: =+SUM(Q20:Q23) -> 0 | ... S19: =+SUM(S20:S23) -> 2835.2364 | T19: =+SUM(T20:T22) -> 61260.351 | U19: =+SUM(U20:U23) -> 21181.087 | V19: =+SUM(V20:V23) -> 0 | W19: =+SUM(W20:W23) -> 0 | X19: =+SUM(X20:X23) -> 0
E20: 1) | F20: diperdagangkan | H20: 10421 | I20: =ROUND(SUM(J20:X20),0) -> 0 | J20: =J21*$Z$21 -> 0 | K20: =K21*$Z$21 -> 0 | L20: =L21*$Z$21 -> 0 | M20: =M21*$Z$21 -> 0 | N20: =N21*$Z$21 -> 0 | W20: =W21/1000 -> 0 | X20: =X21/1000 -> 0
E21: 2) | F21: tersedia untuk dijual | H21: 10422 | I21: =ROUND(SUM(J21:X21),0) -> 78737 | J21: 0 | K21: 0 | L21: 0 | M21: 0 | N21: 0 | O21: 1883.193 | P21: 7689.7319 | Q21: 0 | R21: 0 | S21: 2835.2364 | T21: 60260.12 | U21: 6068.7034 | V21: 0 | W21: 0 | X21: 0
E22: 3) | F22: dimiliki hingga jatuh tempo | H22: 10423 | I22: =ROUND(SUM(J22:X22),0) -> 18111 | J22: 0 | K22: 0 | L22: 0 | M22: 0 | N22: 0 | O22: 1998.7485 | P22: 0 | Q22: 0 | R22: 0 | S22: 0 | T22: 1000.231 | U22: 15112.384 | V22: 0 | W22: 0 | X22: 0
E23: 4) | F23: pinjaman yang diberikan dan piutang | H23: 10424 | I23: =ROUND(SUM(J23:X23),0) -> 0 | W23: =W22/1000 -> 0
D24: b. | E24: Lainnya | H24: 10490 | I24: =ROUND(SUM(J24:X24),0) -> 0
C25: 5. | D25: Kredit Yang Diberikan | H25: 10500 | I25: =ROUND(SUM(J25:X25),0) -> 888790 | J25: =+SUM(J26:J27) -> 45.180168 | K25: =+SUM(K26:K27) -> 0 | L25: =+SUM(L26:L27) -> 0 | M25: =+SUM(M26:M27) -> 8821.6561 | N25: =+SUM(N26:N27) -> 19867.907 | O25: =+SUM(O26:O27) -> 27835.24 | P25: =+SUM(P26:P27) -> 8440.7886 | Q25: =+SUM(Q26:Q27) -> 207723.6 | ... X25: =+SUM(X26:X27) -> 0
D26: a. | E26: belum jatuh tempo | H26: 10510 | I26: =ROUND(SUM(J26:X26),0) -> 888790 | J26: 45.180168 | K26: 0 | L26: 0 | M26: 8821.6561 | N26: 19867.907 | O26: 27835.24 | P26: 8440.7886 | Q26: 207723.6 | R26: 455780.4 | S26: 30413.419 | T26: 44958.888 | U26: 84903.311 | V26: 0 | W26: 0
D27: b. | E27: sudah jatuh tempo ***) | H27: 10520 | I27: =ROUND(SUM(J27:X27),0) -> 0 | Z27: 0 | AA27: 0 | AB27: 0 | AC27: 0
C28: 6. | D28: Tagihan lainnya | H28: 10700 | I28: =ROUND(SUM(J28:X28),0) -> 0 | J28: =+SUM(J29:J30) -> 0 | K28: =+SUM(K29:K30) -> 0 | L28: =+SUM(L29:L30) -> 0 | M28: =+SUM(M29:M30) -> 0 | N28: =+SUM(N29:N30) -> 0 | O28: =+SUM(O29:O30) -> 0 | P28: =+SUM(P29:P30) -> 0 | Q28: =+SUM(Q29:Q30) -> 0 | ... X28: =+SUM(X29:X30) -> 0
D29: a. | E29: Tagihan atas Surat Berharga yang dibeli dengan janji dijual kembali (Reverse Repo) | H29: 10710 | I29: =ROUND(SUM(J29:X29),0) -> 0 | R29: 0 | S29: 0 | T29: 0 | U29: 0 | V29: 0 | W29: 0 | X29: 0
D30: b. | E30: Lainnya | H30: 10790 | I30: =ROUND(SUM(J30:X30),0) -> 0 | S30: 0 | T30: 0 | U30: 0 | V30: 0 | W30: 0 | X30: 0
C31: 7. | D31: Lain-lain | H31: 10600 | I31: =ROUND(SUM(J31:X31),0) -> 43200 | J31: 43200.245 | N31: 0 | O31: 0 | P31: 0 | Q31: 0 | R31: 0 | S31: 0 | T31: 0 | U31: 0 | V31: 0 | W31: 0 | X31: 0
B34: B. | C34: Kewajiban | H34: 20000 | I34: =ROUND(SUM(J34:X34),0) -> 1189497 | J34: =ROUND(+J35+J42+J43+J44+J48+J51+J54,0) -> 36097 | K34: =ROUND(+K35+K42+K43+K44+K48+K51+K54,0) -> 0 | L34: =ROUND(+L35+L42+L43+L44+L48+L51+L54,0) -> 28671 | M34: =ROUND(+M35+M42+M43+M44+M48+M51+M54,0) -> 197320 | N34: =ROUND(+N35+N42+N43+N44+N48+N51+N54,0) -> 356505 | O34: =ROUND(+O35+O42+O43+O44+O48+O51+O54,0) -> 27739 | P34: =ROUND(+P35+P42+P43+P44+P48+P51+P54,0) -> 167996 | Q34: =ROUND(+Q35+Q42+Q43+Q44+Q48+Q51+Q54,0) -> 0 | ... X34: =ROUND(+X35+X42+X43+X44+X48+X51+X54,0) -> 30000
C35: 1. | D35: Dana Pihak Ketiga | H35: 20100 | I35: =ROUND(SUM(J35:X35),0) -> 193801 | J35: =+J36+J37+J38 -> 36097.286 | K35: =+K36+K37+K38 -> 0 | L35: =+L36+L37+L38 -> 0 | M35: =+M36+M37+M38 -> 742.31957 | N35: =+N36+N37+N38 -> 52592.767 | O35: =+O36+O37+O38 -> 0 | P35: =+P36+P37+P38 -> 104368.45 | Q35: =+Q36+Q37+Q38 -> 0 | ... X35: =+X36+X37+X38 -> 0
D36: a. | E36: Giro | H36: 20110 | I36: =ROUND(SUM(J36:X36),0) -> 36097 | J36: =36097285.7/1000 -> 36097.286 | L36: 0 | N36: 0 | P36: 0 | Q36: 0 | R36: 0 | S36: 0 | T36: 0 | U36: 0 | V36: 0 | W36: 0 | X36: 0
D37: b. | E37: Tabungan | H37: 20120 | I37: =ROUND(SUM(J37:X37),0) -> 0 | K37: 0 | L37: 0 | M37: 0 | N37: 0 | P37: 0 | Q37: 0 | R37: 0 | S37: 0 | T37: 0 | U37: 0 | V37: 0 | W37: 0 | X37: 0
D38: c. | E38: Simpanan Berjangka | H38: 20130 | I38: =ROUND(SUM(J38:X38),0) -> 157704 | J38: =+SUM(J39:J41) -> 0 | K38: =+SUM(K39:K41) -> 0 | L38: =+SUM(L39:L41) -> 0 | M38: =+SUM(M39:M41) -> 742.31957 | N38: =+SUM(N39:N41) -> 52592.767 | O38: =+SUM(O39:O41) -> 0 | P38: =+SUM(P39:P41) -> 104368.45 | Q38: =+SUM(Q39:Q41) -> 0 | ... X38: =+SUM(X39:X41) -> 0
E39: 1) | F39: Deposit on call | H39: 20131 | I39: =ROUND(SUM(J39:X39),0) -> 0 | J39: 0 | K39: 0 | L39: 0 | M39: 0 | N39: 0 | O39: 0 | P39: 0 | Q39: 0 | R39: 0 | S39: 0 | T39: 0 | U39: 0 | V39: 0 | W39: 0 | X39: 0
E40: 2) | F40: Deposito berjangka | H40: 20132 | I40: =ROUND(SUM(J40:X40),0) -> 157704 | M40: 742.31957 | N40: 52592.767 | O40: 0 | P40: 104368.45 | Q40: 0 | R40: 0 | S40: 0 | T40: 0 | U40: 0 | V40: 0 | W40: 0 | X40: 0
E41: 3) | F41: Lainnya | H41: 20139 | I41: =ROUND(SUM(J41:X41),0) -> 0
C42: 2. | D42: Kewajiban kepada Bank Indonesia | H42: 20200 | I42: =ROUND(SUM(J42:X42),0) -> 0
C43: 3. | D43: Kewajiban kepada bank lain | H43: 20300 | I43: =ROUND(SUM(J43:X43),0) -> 991773 | J43: 0 | K43: 0 | L43: =48670.6316735322-20000 -> 28670.632 | M43: 192654.58 | N43: =283912.018095605+20000 -> 303912.02 | O43: 27738.612 | P43: 63627.9 | Q43: 0 | R43: 0 | S43: =344750.30768752+419.14 -> 345169.45 | T43: 0 | U43: 0 | V43: 0 | W43: 0 | X43: 30000
C44: 4. | D44: Surat Berharga yang Diterbitkan | H44: 20400 | I44: =ROUND(SUM(J44:X44),0) -> 0 | J44: =+SUM(J45:J47) -> 0 | K44: =+SUM(K45:K47) -> 0 | L44: =+SUM(L45:L47) -> 0 | M44: =+SUM(M45:M47) -> 0 | N44: =+SUM(N45:N47) -> 0 | O44: =+SUM(O45:O47) -> 0 | P44: =+SUM(P45:P47) -> 0 | Q44: =+SUM(Q45:Q47) -> 0 | ... X44: =+SUM(X45:X47) -> 0
D45: a. | E45: Obligasi | H45: 20410 | I45: =ROUND(SUM(J45:X45),0) -> 0
D46: b. | E46: Subordinasi ****) | H46: 20420 | I46: =ROUND(SUM(J46:X46),0) -> 0
D47: c. | E47: Lainnya | H47: 20490 | I47: =ROUND(SUM(J47:X47),0) -> 0 | J47: 0 | K47: 0 | L47: 0 | M47: 0 | N47: 0 | O47: 0 | P47: 0 | Q47: 0 | R47: 0 | S47: 0 | T47: 0 | U47: 0 | V47: 0 | W47: 0 | X47: 0
C48: 5. | D48: Pinjaman yang Diterima | H48: 20500 | I48: =ROUND(SUM(J48:X48),0) -> 0 | J48: =+SUM(J49:J50) -> 0 | K48: =+SUM(K49:K50) -> 0 | L48: =+SUM(L49:L50) -> 0 | M48: =+SUM(M49:M50) -> 0 | N48: =+SUM(N49:N50) -> 0 | O48: =+SUM(O49:O50) -> 0 | P48: =+SUM(P49:P50) -> 0 | Q48: =+SUM(Q49:Q50) -> 0 | ... X48: =+SUM(X49:X50) -> 0
D49: a. | E49: Pinjaman Subordinasi ****) | H49: 20510 | I49: =ROUND(SUM(J49:X49),0) -> 0 | J49: 0 | K49: 0 | L49: 0 | M49: 0 | N49: 0 | O49: 0 | P49: 0 | Q49: 0 | R49: 0 | S49: 0 | T49: 0 | U49: 0 | V49: 0 | W49: 0 | X49: 0
D50: b. | E50: Lainnya | H50: 20590 | I50: =ROUND(SUM(J50:X50),0) -> 0 | J50: 0 | K50: 0 | L50: 0 | M50: 0 | N50: 0 | O50: 0 | P50: 0 | Q50: 0 | R50: 0 | S50: 0 | T50: 0 | U50: 0 | V50: 0 | W50: 0 | X50: 0
C51: 6. | D51: Kewajiban lainnya | H51: 20700 | I51: =ROUND(SUM(J51:X51),0) -> 0 | J51: =+SUM(J52:J53) -> 0 | K51: =+SUM(K52:K53) -> 0 | L51: =+SUM(L52:L53) -> 0 | M51: =+SUM(M52:M53) -> 0 | N51: =+SUM(N52:N53) -> 0 | O51: =+SUM(O52:O53) -> 0 | P51: =+SUM(P52:P53) -> 0 | Q51: =+SUM(Q52:Q53) -> 0 | ... X51: =+SUM(X52:X53) -> 0
D52: a. | E52: Kewajiban atas Surat Berharga yang dijual dengan janji dibeli kembali (Repo) | H52: 20710 | I52: =ROUND(SUM(J52:X52),0) -> 0 | J52: 0 | K52: 0 | L52: 0 | M52: 0 | N52: 0 | O52: 0 | P52: 0 | Q52: 0 | R52: 0 | S52: 0 | T52: 0 | U52: 0 | V52: 0 | W52: 0 | X52: 0
D53: b. | E53: Lainnya | H53: 20790 | I53: =ROUND(SUM(J53:X53),0) -> 0 | J53: 0 | K53: 0 | L53: 0 | M53: 0 | N53: 0 | O53: 0 | P53: 0 | Q53: 0 | R53: 0 | S53: 0 | T53: 0 | U53: 0 | V53: 0 | W53: 0 | X53: 0
C54: 7. | D54: Lain-lain | H54: 20600 | I54: =ROUND(SUM(J54:X54),0) -> 3923 | M54: 3922.9929 | P54: 0 | Q54: 0 | R54: 0 | S54: 0 | T54: 0 | U54: 0 | V54: 0 | W54: 0 | X54: 0
B56: C. Selisih Aset dengan Kewajiban dalam Neraca | H56: 30000 | I56: =ROUND(SUM(J56:X56),0) -> 0 | J56: =+J14-J34 -> 52349 | K56: =+K14-K34 -> 0 | L56: =+L14-L34 -> -28671 | M56: =+M14-M34 -> -188498 | N56: =+N14-N34 -> -336637 | O56: =+O14-O34 -> 3978 | P56: =+P14-P34 -> -151865 | Q56: =+Q14-Q34 -> 207724 | ... X56: =+X14-X34 -> -30000
B58: II | C58: REKENING ADMINISTRATIF
B59: A. | C59: Tagihan Rekening Administratif | H59: 40000 | I59: =ROUND(SUM(J59:X59),0) -> 0 | J59: =+J60+J66 -> 0 | K59: =+K60+K66 -> 0 | L59: =+L60+L66 -> 0 | M59: =+M60+M66 -> 0 | N59: =+N60+N66 -> 0 | O59: =+O60+O66 -> 0 | P59: =+P60+P66 -> 0 | Q59: =+Q60+Q66 -> 0 | ... X59: =+X60+X66 -> 0
C60: 1. | D60: Komitmen | H60: 40100 | I60: =ROUND(SUM(J60:X60),0) -> 0 | J60: =+J61+J62+J65 -> 0 | K60: =+K61+K62+K65 -> 0 | L60: =+L61+L62+L65 -> 0 | M60: =+M61+M62+M65 -> 0 | N60: =+N61+N62+N65 -> 0 | O60: =+O61+O62+O65 -> 0 | P60: =+P61+P62+P65 -> 0 | Q60: =+Q61+Q62+Q65 -> 0 | ... X60: =+X61+X62+X65 -> 0
D61: a. | E61: Fasilitas pinjaman yang belum ditarik | H61: 40110 | I61: =ROUND(SUM(J61:X61),0) -> 0 | J61: 0 | L61: 0 | M61: 0 | N61: 0 | O61: 0 | P61: 0 | Q61: 0 | R61: 0 | S61: 0 | T61: 0 | U61: 0 | V61: 0 | W61: 0 | X61: 0
D62: b. | E62: Posisi pembelian spot dan derivatif yang masih berjalan | H62: 40120 | I62: =ROUND(SUM(J62:X62),0) -> 0 | J62: =+J63+J64 -> 0 | K62: =+K63+K64 -> 0 | L62: =+L63+L64 -> 0 | M62: =+M63+M64 -> 0 | N62: =+N63+N64 -> 0 | O62: =+O63+O64 -> 0 | P62: =+P63+P64 -> 0 | Q62: =+Q63+Q64 -> 0 | ... X62: =+X63+X64 -> 0
E63: 1) | F63: Spot | H63: 40121 | I63: =ROUND(SUM(J63:X63),0) -> 0 | J63: 0 | K63: 0 | L63: 0 | M63: 0 | N63: 0 | O63: 0 | P63: 0 | Q63: 0 | R63: 0 | S63: 0 | T63: 0 | U63: 0 | V63: 0 | W63: 0 | X63: 0
E64: 2) | F64: Derivatif | H64: 40122 | I64: =ROUND(SUM(J64:X64),0) -> 0 | J64: 0 | K64: 0 | L64: 0 | M64: 0 | N64: 0 | O64: 0 | P64: 0 | Q64: 0 | R64: 0 | S64: 0 | T64: 0 | U64: 0 | V64: 0 | W64: 0 | X64: 0
D65: c. | E65: Lainnya | H65: 40190 | I65: =ROUND(SUM(J65:X65),0) -> 0 | K65: 0 | L65: 0 | M65: 0 | N65: 0 | O65: 0 | P65: 0 | Q65: 0 | R65: 0 | S65: 0 | T65: 0 | U65: 0 | V65: 0 | W65: 0 | X65: 0
C66: 2. | D66: Kontijensi *****) | H66: 40200 | I66: =ROUND(SUM(J66:X66),0) -> 0 | J66: 0 | K66: 0 | L66: 0 | M66: 0 | N66: 0 | O66: 0 | P66: 0 | Q66: 0 | R66: 0 | S66: 0 | T66: 0 | U66: 0 | V66: 0 | W66: 0 | X66: 0
B68: B. | C68: Kewajiban Rekening Administratif | H68: 50000 | I68: =ROUND(SUM(J68:X68),0) -> 0 | J68: =+J69+J76 -> 0 | K68: =+K69+K76 -> 0 | L68: =+L69+L76 -> 0 | M68: =+M69+M76 -> 0 | N68: =+N69+N76 -> 0 | O68: =+O69+O76 -> 0 | P68: =+P69+P76 -> 0 | Q68: =+Q69+Q76 -> 0 | ... X68: =+X69+X76 -> 0
C69: 1. | D69: Komitmen | H69: 50100 | I69: =ROUND(SUM(J69:X69),0) -> 0 | J69: =+J70+J71+J72+J75 -> 0 | K69: =+K70+K71+K72+K75 -> 0 | L69: =+L70+L71+L72+L75 -> 0 | M69: =+M70+M71+M72+M75 -> 0 | N69: =+N70+N71+N72+N75 -> 0 | O69: =+O70+O71+O72+O75 -> 0 | P69: =+P70+P71+P72+P75 -> 0 | Q69: =+Q70+Q71+Q72+Q75 -> 0 | ... X69: =+X70+X71+X72+X75 -> 0
D70: a. | E70: Fasilitas kredit yang belum ditarik | H70: 50110 | I70: =ROUND(SUM(J70:X70),0) -> 0 | J70: 0 | K70: 0 | L70: 0 | M70: 0 | N70: 0 | O70: 0 | P70: 0 | Q70: 0 | R70: 0 | S70: 0 | T70: 0 | U70: 0 | V70: 0 | W70: 0 | X70: 0
D71: b. | E71: Irrevocable L/C yang masih berjalan | H71: 50120 | I71: =ROUND(SUM(J71:X71),0) -> 0 | J71: 0 | K71: 0 | L71: 0 | M71: 0 | N71: 0 | O71: 0 | P71: 0 | Q71: 0 | R71: 0 | S71: 0 | T71: 0 | U71: 0 | V71: 0 | W71: 0 | X71: 0
D72: c. | E72: Posisi penjualan spot dan derivatif yang masih berjalan | H72: 50130 | I72: =ROUND(SUM(J72:X72),0) -> 0 | J72: =+J73+J74 -> 0 | K72: =+K73+K74 -> 0 | L72: =+L73+L74 -> 0 | M72: =+M73+M74 -> 0 | N72: =+N73+N74 -> 0 | O72: =+O73+O74 -> 0 | P72: =+P73+P74 -> 0 | Q72: =+Q73+Q74 -> 0 | ... X72: =+X73+X74 -> 0
E73: 1) | F73: Spot | H73: 50131 | I73: =ROUND(SUM(J73:X73),0) -> 0 | J73: 0 | K73: 0 | L73: 0 | M73: 0 | N73: 0 | O73: 0 | P73: 0 | Q73: 0 | R73: 0 | S73: 0 | T73: 0 | U73: 0 | V73: 0 | W73: 0 | X73: 0
E74: 2) | F74: Derivatif | H74: 50132 | I74: =ROUND(SUM(J74:X74),0) -> 0 | J74: 0 | K74: 0 | L74: 0 | M74: 0 | N74: 0 | O74: 0 | P74: 0 | Q74: 0 | R74: 0 | S74: 0 | T74: 0 | U74: 0 | V74: 0 | W74: 0 | X74: 0
D75: d. | E75: Lainnya | H75: 50190 | I75: =ROUND(SUM(J75:X75),0) -> 0 | J75: 0 | K75: 0 | L75: 0 | M75: 0 | N75: 0 | O75: 0 | P75: 0 | Q75: 0 | R75: 0 | S75: 0 | T75: 0 | U75: 0 | V75: 0 | W75: 0 | X75: 0
C76: 2. | D76: Kontijensi ******) | H76: 50200 | I76: =ROUND(SUM(J76:X76),0) -> 0 | K76: 0 | L76: 0 | M76: 0 | P76: 0 | Q76: 0 | R76: 0 | S76: 0 | T76: 0 | U76: 0 | V76: 0 | W76: 0 | X76: 0
B78: C. Selisih Tagihan dan Kewajiban dalam Rekening Administratif | H78: 60000 | I78: =ROUND(SUM(J78:X78),0) -> 0 | J78: =+J59-J68 -> 0 | K78: =+K59-K68 -> 0 | L78: =+L59-L68 -> 0 | M78: =+M59-M68 -> 0 | N78: =+N59-N68 -> 0 | O78: =+O59-O68 -> 0 | P78: =+P59-P68 -> 0 | Q78: =+Q59-Q68 -> 0 | ... X78: =+X59-X68 -> 0
B80: Selisih [(IA-IB)+(IIA-IIB)] | H80: 70000 | I80: 0 | J80: =+J56+J78 -> 52349 | K80: =+K56+K78 -> 0 | L80: =+L56+L78 -> -28671 | M80: =+M56+M78 -> -188498 | N80: =+N56+N78 -> -336637 | O80: =+O56+O78 -> 3978 | P80: =+P56+P78 -> -151865 | Q80: =+Q56+Q78 -> 207724 | ... X80: =+X56+X78 -> -30000
B82: Selisih Kumulatif | H82: 80000 | I82: =+I80 -> 0 | J82: =+I82+J80 -> 52349 | K82: =+J82+K80 -> 52349 | L82: =+K82+L80 -> 23678 | M82: =+L82+M80 -> -164820 | N82: =+M82+N80 -> -501457 | O82: =+N82+O80 -> -497479 | P82: =+O82+P80 -> -649344 | Q82: =+P82+Q80 -> -441620 | ... X82: =+W82+X80 -> 0
C85: *) | D85: Angka-angka berdasarkan jatuh tempo sesuai dengan kontrak untuk yang memiliki jatuh tempo kontraktual dan/atau estimasi dengan menggunakan berbagai asumsi untuk yang tidak memiliki jatuh tempo kontraktual | U85: PT Bank Negara Indonesia (Persero) Tbk.
C86: **) | D86: Termasuk Surat Berharga yang dijual dengan janji dibeli kembali (Repo)
C87: ***) | D87: Diisi berdasarkan perkiraan diperoleh pembayaran atas kredit yang berdasarkan kontrak sudah jatuh tempo
C88: ****) | D88: Termasuk yang diperhitungkan dalam KPMM dan dilaporkan di LBU pada pos Modal Pinjaman
C89: *****) | D89: Yang diperkirakan akan mempengaruhi arus kas (menjadi tagihan)
C90: ******) | D90: Yang diperkirakan akan mempengaruhi arus kas (menjadi kewajiban)
C92: catatan: Core Giro non bank berdasarkan data historis selama Dua (2) tahun.
B98: Catatan:
B99: ¨ | C99: Pos-pos dalam maturity profile diisi sesuai pembukuan Bank Pelapor berdasarkan sisa waktu sampai dengan jatuh tempo sesuai kontrak untuk pos neraca dan rekening administratif yang memiliki jatuh tempo kontraktual dan/ atau asumsi utk pos neraca dan rekening administratif yang tidak memiliki jatuh tempo kontraktual (non maturity items)
B103: ¨ | C103: Yang dimasukkan dalam pos-pos neraca adalah hanya pos-pos dengan karakteristik memiliki arus kas masuk / atau arus kas keluar, sehingga tidak seluruh pos di neraca di masukkan dalam laporan ini. Contoh pos neraca yang tidak dimasukkan dalam laporan ini antara lain asset tetap, AYDA, properti terbengkalai, penyertaan, dan modal
B108: ¨ | C108: Sebagai kontrol, agar sesuai dengan neraca (balance antara asset & liability --> Total Asset - Total Liability = 0 di kolom saldo (H)), maka pos-pos yang tidak dimasukkan ke dalam maturity profile tetap dimasukkan ke pos poin 7. Lainnya diletakkan di kolom (P).
C119: Tagihan --> Buy
C120: Kewajiban --> Sell

Sheet NY
A2: A | B2: B | C2: C | D2: D | E2: E | F2: F | G2: G | I2: H | J2: I | K2: J | L2: K | M2: L | N2: M | O2: N
B3: Formulir 4.b.
B4: MATURITY PROFILE REPORT - BNI NEW YORK AGENCY
B5: CONTRACTUAL BASED
B6: 45777
B7: Valuta Asing
I8: LIABILITIES KUMULATIF S.D 1 BULAN | J8: =O9 -> 1318744.6 | M8: =SUM(J14:L14) -> 1406607 | N8: =SUM(J59:L59) -> 37990.588 | O8: =M8+N8 -> 1444597.6 | P8: aset | Q8: =O8/O9 -> 1.0954339
I9: ASSET KUMULATIF S.D 1 BULAN | J9: =O8 -> 1444597.6 | K9: =+J9-J8 -> 125853 | L9: =+J9/J8*10000% -> 109.54339 | M9: =SUM(J34:L34) -> 1280754 | N9: =SUM(J68:L68) -> 37990.588 | O9: =+M9+N9 -> 1318744.6 | P9: kewajiban | W9: in Thousand USD
B10: Pos-Pos | H10: Sandi | I10: Saldo | J10: Time to Maturity *)
J11: up to 1 week | K11: > 1 week to 2 weeks | L11: > 2 weeks to 1 month | M11: > 1 month to 3 months | N11: > 3 months to 6 months | O11: > 6 months to 1 year | P11: > 1 y to 2 y | Q11: > 2 y to 3 y | R11: > 3 y to 4 y | S11: > 4 y to 5 y | T11: > 5 y to 7 y | U11: > 7 y to 10 y | V11: > 10 y to 15 y | W11: > 15 y to 20 y | X11: > 20 y
B13: I. | C13: NERACA
B14: A. | C14: Aset | H14: 10000 | I14: =ROUND(SUM(J14:X14),0) -> 2287215 | J14: =ROUND(+J15+J16+J17+J18+J25+J28+J31,0) -> 1360572 | K14: =ROUND(+K15+K16+K17+K18+K25+K28+K31,0) -> 42218 | L14: =ROUND(+L15+L16+L17+L18+L25+L28+L31,0) -> 3817 | M14: =ROUND(+M15+M16+M17+M18+M25+M28+M31,0) -> 45651 | N14: =ROUND(+N15+N16+N17+N18+N25+N28+N31,0) -> 30627 | O14: =ROUND(+O15+O16+O17+O18+O25+O28+O31,0) -> 56775 | P14: =ROUND(+P15+P16+P17+P18+P25+P28+P31,0) -> 122252 | Q14: =ROUND(+Q15+Q16+Q17+Q18+Q25+Q28+Q31,0) -> 262744 | ... X14: =ROUND(+X15+X16+X17+X18+X25+X28+X31,0) -> 3210
C15: 1. | D15: Kas | H15: 10100 | I15: =ROUND(SUM(J15:X15),0) -> 1 | J15: =+'[2]Maturity Profile (Eng)'!J15 -> 0.5401 | K15: =+'[2]Maturity Profile (Eng)'!K15 -> 0 | L15: =+'[2]Maturity Profile (Eng)'!L15 -> 0 | M15: =+'[2]Maturity Profile (Eng)'!M15 -> 0 | N15: =+'[2]Maturity Profile (Eng)'!N15 -> 0 | O15: =+'[2]Maturity Profile (Eng)'!O15 -> 0 | P15: =+'[2]Maturity Profile (Eng)'!P15 -> 0 | Q15: =+'[2]Maturity Profile (Eng)'!Q15 -> 0 | ... X15: =+'[2]Maturity Profile (Eng)'!X15 -> 0 | Y15: x | Z15: PRT.GLAJ650.PER - 100001 NY
C16: 2. | D16: Penempatan pada Bank Indonesia | H16: 10200 | I16: =ROUND(SUM(J16:X16),0) -> 0 | J16: =+'[2]Maturity Profile (Eng)'!J16 -> 0 | K16: =+'[2]Maturity Profile (Eng)'!K16 -> 0 | L16: =+'[2]Maturity Profile (Eng)'!L16 -> 0 | M16: =+'[2]Maturity Profile (Eng)'!M16 -> 0 | N16: =+'[2]Maturity Profile (Eng)'!N16 -> 0 | O16: =+'[2]Maturity Profile (Eng)'!O16 -> 0 | P16: =+'[2]Maturity Profile (Eng)'!P16 -> 0 | Q16: =+'[2]Maturity Profile (Eng)'!Q16 -> 0 | ... X16: =+'[2]Maturity Profile (Eng)'!X16 -> 0 | Z16: NOT AVAILABLE
C17: 3. | D17: Penempatan pada bank lain | H17: 10300 | I17: =ROUND(SUM(J17:X17),0) -> 1422989 | J17: =+'[2]Maturity Profile (Eng)'!J17 -> 1358988.6 | K17: =+'[2]Maturity Profile (Eng)'!K17 -> 40000 | L17: =+'[2]Maturity Profile (Eng)'!L17 -> 0 | M17: =+'[2]Maturity Profile (Eng)'!M17 -> 24000 | N17: =+'[2]Maturity Profile (Eng)'!N17 -> 0 | O17: =+'[2]Maturity Profile (Eng)'!O17 -> 0 | P17: =+'[2]Maturity Profile (Eng)'!P17 -> 0 | Q17: =+'[2]Maturity Profile (Eng)'!Q17 -> 0 | ... X17: =+'[2]Maturity Profile (Eng)'!X17 -> 0 | Y17: x | Z17: PRT.GLAJ650.PER - (NY) 102001+(NY) 102002+(IBF)110103 | AF17: =(243578452.62+130258.76+140000000)/1000 -> 383708.71
C18: 4. | D18: Surat Berharga **) | H18: 10400 | I18: =ROUND(SUM(J18:X18),0) -> 142900 | J18: =+J19+J24 -> 0 | K18: =+K19+K24 -> 0 | L18: =+L19+L24 -> 0 | M18: =+M19+M24 -> 5005.35 | N18: =+N19+N24 -> 0 | O18: =+O19+O24 -> 7482.2732 | P18: =+P19+P24 -> 13396.151 | Q18: =+Q19+Q24 -> 0 | ... X18: =+X19+X24 -> 3209.9
D19: a. | E19: Surat berharga korporasi | H19: 10420 | I19: =ROUND(SUM(J19:X19),0) -> 142900 | J19: =+SUM(J20:J23) -> 0 | K19: =+SUM(K20:K23) -> 0 | L19: =+SUM(L20:L23) -> 0 | M19: =+SUM(M20:M23) -> 5005.35 | N19: =+SUM(N20:N23) -> 0 | O19: =+SUM(O20:O23) -> 7482.2732 | P19: =+SUM(P20:P23) -> 13396.151 | Q19: =+SUM(Q20:Q23) -> 0 | ... X19: =+SUM(X20:X23) -> 3209.9
E20: 1) | F20: diperdagangkan | H20: 10421 | I20: =ROUND(SUM(J20:X20),0) -> 0 | J20: =+'[2]Maturity Profile (Eng)'!J20 -> 0 | K20: =+'[2]Maturity Profile (Eng)'!K20 -> 0 | L20: =+'[2]Maturity Profile (Eng)'!L20 -> 0 | M20: =+'[2]Maturity Profile (Eng)'!M20 -> 0 | N20: =+'[2]Maturity Profile (Eng)'!N20 -> 0 | O20: =+'[2]Maturity Profile (Eng)'!O20 -> 0 | P20: =+'[2]Maturity Profile (Eng)'!P20 -> 0 | Q20: =+'[2]Maturity Profile (Eng)'!Q20 -> 0 | ... X20: =+'[2]Maturity Profile (Eng)'!X20 -> 0
E21: 2) | F21: tersedia untuk dijual | H21: 10422 | I21: =ROUND(SUM(J21:X21),0) -> 74837 | J21: =+'[2]Maturity Profile (Eng)'!J21 -> 0 | K21: =+'[2]Maturity Profile (Eng)'!K21 -> 0 | L21: =+'[2]Maturity Profile (Eng)'!L21 -> 0 | M21: =+'[2]Maturity Profile (Eng)'!M21 -> 5005.35 | N21: =+'[2]Maturity Profile (Eng)'!N21 -> 0 | O21: =+'[2]Maturity Profile (Eng)'!O21 -> 4980.75 | P21: =+'[2]Maturity Profile (Eng)'!P21 -> 7390.6633 | Q21: =+'[2]Maturity Profile (Eng)'!Q21 -> 0 | ... X21: =+'[2]Maturity Profile (Eng)'!X21 -> 3209.9 | Y21: x | Z21: PRT.GLAJ650.PER - 115127+115130+115132+115135+115136+115182+115183 | AH21: =(60500000+12978.45+30000000+7500000+3633905.36+513059.34)/1000 -> 102159.94 | AI21: =I21 -> 74837 | AJ21: =AH21-AI21 -> 27322.943 | AK21: *difference due to accounting
E22: 3) | F22: dimiliki hingga jatuh tempo | H22: 10423 | I22: =ROUND(SUM(J22:X22),0) -> 68063 | J22: =+'[2]Maturity Profile (Eng)'!J22 -> 0 | K22: =+'[2]Maturity Profile (Eng)'!K22 -> 0 | L22: =+'[2]Maturity Profile (Eng)'!L22 -> 0 | M22: =+'[2]Maturity Profile (Eng)'!M22 -> 0 | N22: =+'[2]Maturity Profile (Eng)'!N22 -> 0 | O22: =+'[2]Maturity Profile (Eng)'!O22 -> 2501.5232 | P22: =+'[2]Maturity Profile (Eng)'!P22 -> 6005.4873 | Q22: =+'[2]Maturity Profile (Eng)'!Q22 -> 0 | ... X22: =+'[2]Maturity Profile (Eng)'!X22 -> 0 | Y22: x | Z22: PRT.GLAJ650.PER - 115147+115155+115156+115181 | AE22: =(70500000-418782.02)/1000 -> 70081.218 | AF22: =I22 -> 68063 | AG22: =AF22-AE22 -> -2018.218
E23: 4) | F23: pinjaman yang diberikan dan piutang | H23: 10424 | I23: =ROUND(SUM(J23:X23),0) -> 0 | J23: =+'[2]Maturity Profile (Eng)'!J23 -> 0 | K23: =+'[2]Maturity Profile (Eng)'!K23 -> 0 | L23: =+'[2]Maturity Profile (Eng)'!L23 -> 0 | M23: =+'[2]Maturity Profile (Eng)'!M23 -> 0 | N23: =+'[2]Maturity Profile (Eng)'!N23 -> 0 | O23: =+'[2]Maturity Profile (Eng)'!O23 -> 0 | P23: =+'[2]Maturity Profile (Eng)'!P23 -> 0 | Q23: =+'[2]Maturity Profile (Eng)'!Q23 -> 0 | ... X23: =+'[2]Maturity Profile (Eng)'!X23 -> 0 | AA23: repo= 115144-115181 | AE23: 0
D24: b. | E24: Lainnya | H24: 10490 | I24: =ROUND(SUM(J24:X24),0) -> 0 | J24: =+'[2]Maturity Profile (Eng)'!J24 -> 0 | K24: =+'[2]Maturity Profile (Eng)'!K24 -> 0 | L24: =+'[2]Maturity Profile (Eng)'!L24 -> 0 | M24: =+'[2]Maturity Profile (Eng)'!M24 -> 0 | N24: =+'[2]Maturity Profile (Eng)'!N24 -> 0 | O24: =+'[2]Maturity Profile (Eng)'!O24 -> 0 | P24: =+'[2]Maturity Profile (Eng)'!P24 -> 0 | Q24: =+'[2]Maturity Profile (Eng)'!Q24 -> 0 | ... X24: =+'[2]Maturity Profile (Eng)'!X24 -> 0
C25: 5. | D25: Kredit Yang Diberikan | H25: 10500 | I25: =ROUND(SUM(J25:X25),0) -> 721326 | J25: =+SUM(J26:J27) -> 1583.2945 | K25: =+SUM(K26:K27) -> 2218.35 | L25: =+SUM(L26:L27) -> 3816.9479 | M25: =+SUM(M26:M27) -> 16646.088 | N25: =+SUM(N26:N27) -> 30627.221 | O25: =+SUM(O26:O27) -> 49292.513 | P25: =+SUM(P26:P27) -> 108855.87 | Q25: =+SUM(Q26:Q27) -> 262743.62 | ... X25: =+SUM(X26:X27) -> 0
D26: a. | E26: belum jatuh tempo | H26: 10510 | I26: =ROUND(SUM(J26:X26),0) -> 721326 | J26: =+'[2]Maturity Profile (Eng)'!J26 -> 1583.2945 | K26: =+'[2]Maturity Profile (Eng)'!K26 -> 2218.35 | L26: =+'[2]Maturity Profile (Eng)'!L26 -> 3816.9479 | M26: =+'[2]Maturity Profile (Eng)'!M26 -> 16646.088 | N26: =+'[2]Maturity Profile (Eng)'!N26 -> 30627.221 | O26: =+'[2]Maturity Profile (Eng)'!O26 -> 49292.513 | P26: =+'[2]Maturity Profile (Eng)'!P26 -> 108855.87 | Q26: =+'[2]Maturity Profile (Eng)'!Q26 -> 262743.62 | ... X26: =+'[2]Maturity Profile (Eng)'!X26 -> 0 | Z26: FROM loan sheet
D27: b. | E27: sudah jatuh tempo ***) | H27: 10520 | I27: =ROUND(SUM(J27:X27),0) -> 0 | J27: =+'[2]Maturity Profile (Eng)'!J27 -> 0 | K27: =+'[2]Maturity Profile (Eng)'!K27 -> 0 | L27: =+'[2]Maturity Profile (Eng)'!L27 -> 0 | M27: =+'[2]Maturity Profile (Eng)'!M27 -> 0 | N27: =+'[2]Maturity Profile (Eng)'!N27 -> 0 | O27: =+'[2]Maturity Profile (Eng)'!O27 -> 0 | P27: =+'[2]Maturity Profile (Eng)'!P27 -> 0 | Q27: =+'[2]Maturity Profile (Eng)'!Q27 -> 0 | ... X27: =+'[2]Maturity Profile (Eng)'!X27 -> 0 | Z27: FROM loan sheet
C28: 6. | D28: Tagihan lainnya | H28: 10700 | I28: =ROUND(SUM(J28:X28),0) -> 0 | J28: =+SUM(J29:J30) -> 0 | K28: =+SUM(K29:K30) -> 0 | L28: =+SUM(L29:L30) -> 0 | M28: =+SUM(M29:M30) -> 0 | N28: =+SUM(N29:N30) -> 0 | O28: =+SUM(O29:O30) -> 0 | P28: =+SUM(P29:P30) -> 0 | Q28: =+SUM(Q29:Q30) -> 0 | ... X28: =+SUM(X29:X30) -> 0
D29: a. | E29: Tagihan atas Surat Berharga yang dibeli dengan janji dijual kembali (Reverse Repo) | H29: 10710 | I29: =ROUND(SUM(J29:X29),0) -> 0 | J29: =+'[2]Maturity Profile (Eng)'!J29 -> 0 | K29: =+'[2]Maturity Profile (Eng)'!K29 -> 0 | L29: =+'[2]Maturity Profile (Eng)'!L29 -> 0 | M29: =+'[2]Maturity Profile (Eng)'!M29 -> 0 | N29: =+'[2]Maturity Profile (Eng)'!N29 -> 0 | O29: =+'[2]Maturity Profile (Eng)'!O29 -> 0 | P29: =+'[2]Maturity Profile (Eng)'!P29 -> 0 | Q29: =+'[2]Maturity Profile (Eng)'!Q29 -> 0 | ... X29: =+'[2]Maturity Profile (Eng)'!X29 -> 0
D30: b. | E30: Lainnya | H30: 10790 | I30: =ROUND(SUM(J30:X30),0) -> 0 | J30: =+'[2]Maturity Profile (Eng)'!J30 -> 0 | K30: =+'[2]Maturity Profile (Eng)'!K30 -> 0 | L30: =+'[2]Maturity Profile (Eng)'!L30 -> 0 | M30: =+'[2]Maturity Profile (Eng)'!M30 -> 0 | N30: =+'[2]Maturity Profile (Eng)'!N30 -> 0 | O30: =+'[2]Maturity Profile (Eng)'!O30 -> 0 | P30: =+'[2]Maturity Profile (Eng)'!P30 -> 0 | Q30: =+'[2]Maturity Profile (Eng)'!Q30 -> 0 | ... X30: =+'[2]Maturity Profile (Eng)'!X30 -> 0 | Y30: x | Z30: PRT.GLAJ650.PER - (NY) 150004 | AD30: ='[3]Export Bills Discounted'!#REF!/1000 -> #REF! | AE30: =I30 -> 0 | AF30: =AD30-AE30 -> #REF!
C31: 7. | D31: Lain-lain | H31: 10600 | I31: =ROUND(SUM(J31:X31),0) -> 0 | J31: =+'[2]Maturity Profile (Eng)'!I31 -> 0 | K31: =+'[2]Maturity Profile (Eng)'!J31 -> 0 | L31: =+'[2]Maturity Profile (Eng)'!K31 -> 0 | M31: =+'[2]Maturity Profile (Eng)'!L31 -> 0 | N31: =+'[2]Maturity Profile (Eng)'!M31 -> 0 | O31: =+'[2]Maturity Profile (Eng)'!N31 -> 0 | P31: =+'[2]Maturity Profile (Eng)'!O31 -> 0 | Q31: =+'[2]Maturity Profile (Eng)'!P31 -> 0 | ... X31: =+'[2]Maturity Profile (Eng)'!W31 -> 0 | Y31: x | Z31: PRT.GLAJ650.PER - (NY) 150001 | AD31: ='[3]TRADE ADVANCE'!D8/1000 -> 0 | AE31: =I31 -> 0 | AF31: =AD31-AE31 -> 0
AF32: .
B34: B. | C34: Kewajiban | H34: 20000 | I34: =ROUND(SUM(J34:X34),0) -> 1448139 | J34: =ROUND(+J35+J42+J43+J44+J48+J51+J54,0) -> 1230854 | K34: =ROUND(+K35+K42+K43+K44+K48+K51+K54,0) -> 2900 | L34: =ROUND(+L35+L42+L43+L44+L48+L51+L54,0) -> 47000 | M34: =ROUND(+M35+M42+M43+M44+M48+M51+M54,0) -> 43585 | N34: =ROUND(+N35+N42+N43+N44+N48+N51+N54,0) -> 0 | O34: =ROUND(+O35+O42+O43+O44+O48+O51+O54,0) -> 8800 | P34: =ROUND(+P35+P42+P43+P44+P48+P51+P54,0) -> 0 | Q34: =ROUND(+Q35+Q42+Q43+Q44+Q48+Q51+Q54,0) -> 0 | ... X34: =ROUND(+X35+X42+X43+X44+X48+X51+X54,0) -> 0
C35: 1. | D35: Dana Pihak Ketiga | H35: 20100 | I35: =ROUND(SUM(J35:X35),0) -> 93239 | J35: =+J36+J37+J38 -> 92853.899 | K35: =+K36+K37+K38 -> 0 | L35: =+L36+L37+L38 -> 0 | M35: =+M36+M37+M38 -> 385 | N35: =+N36+N37+N38 -> 0 | O35: =+O36+O37+O38 -> 0 | P35: =+P36+P37+P38 -> 0 | Q35: =+Q36+Q37+Q38 -> 0 | ... X35: =+X36+X37+X38 -> 0
D36: a. | E36: Giro | H36: 20110 | I36: =ROUND(SUM(J36:X36),0) -> 92854 | J36: =+'[2]Maturity Profile (Eng)'!J36 -> 92853.899 | K36: =+'[2]Maturity Profile (Eng)'!K36 -> 0 | L36: =+'[2]Maturity Profile (Eng)'!L36 -> 0 | M36: =+'[2]Maturity Profile (Eng)'!M36 -> 0 | N36: =+'[2]Maturity Profile (Eng)'!N36 -> 0 | O36: =+'[2]Maturity Profile (Eng)'!O36 -> 0 | P36: =+'[2]Maturity Profile (Eng)'!P36 -> 0 | Q36: =+'[2]Maturity Profile (Eng)'!Q36 -> 0 | ... X36: =+'[2]Maturity Profile (Eng)'!X36 -> 0 | Y36: x | Z36: PRT.GLAJ650.PER - (NY) 210001+210002+210006+251003 | AG36: =+(70600321.76+87577.38+12766595.2+201497.59)/1000 -> 83655.992
D37: b. | E37: Tabungan | H37: 20120 | I37: =ROUND(SUM(J37:X37),0) -> 0 | J37: =+'[2]Maturity Profile (Eng)'!J37 -> 0 | K37: =+'[2]Maturity Profile (Eng)'!K37 -> 0 | L37: =+'[2]Maturity Profile (Eng)'!L37 -> 0 | M37: =+'[2]Maturity Profile (Eng)'!M37 -> 0 | N37: =+'[2]Maturity Profile (Eng)'!N37 -> 0 | O37: =+'[2]Maturity Profile (Eng)'!O37 -> 0 | P37: =+'[2]Maturity Profile (Eng)'!P37 -> 0 | Q37: =+'[2]Maturity Profile (Eng)'!Q37 -> 0 | ... X37: =+'[2]Maturity Profile (Eng)'!X37 -> 0
D38: c. | E38: Simpanan Berjangka | H38: 20130 | I38: =ROUND(SUM(J38:X38),0) -> 385 | J38: =+SUM(J39:J41) -> 0 | K38: =+SUM(K39:K41) -> 0 | L38: =+SUM(L39:L41) -> 0 | M38: =+SUM(M39:M41) -> 385 | N38: =+SUM(N39:N41) -> 0 | O38: =+SUM(O39:O41) -> 0 | P38: =+SUM(P39:P41) -> 0 | Q38: =+SUM(Q39:Q41) -> 0 | ... X38: =+SUM(X39:X41) -> 0
E39: 1) | F39: Deposit on call | H39: 20131 | I39: =ROUND(SUM(J39:X39),0) -> 0 | J39: =+'[2]Maturity Profile (Eng)'!J39 -> 0 | K39: =+'[2]Maturity Profile (Eng)'!K39 -> 0 | L39: =+'[2]Maturity Profile (Eng)'!L39 -> 0 | M39: =+'[2]Maturity Profile (Eng)'!M39 -> 0 | N39: =+'[2]Maturity Profile (Eng)'!N39 -> 0 | O39: =+'[2]Maturity Profile (Eng)'!O39 -> 0 | P39: =+'[2]Maturity Profile (Eng)'!P39 -> 0 | Q39: =+'[2]Maturity Profile (Eng)'!Q39 -> 0 | ... X39: =+'[2]Maturity Profile (Eng)'!X39 -> 0
E40: 2) | F40: Deposito berjangka | H40: 20132 | I40: =ROUND(SUM(J40:X40),0) -> 385 | J40: =+'[2]Maturity Profile (Eng)'!J40 -> 0 | K40: =+'[2]Maturity Profile (Eng)'!K40 -> 0 | L40: =+'[2]Maturity Profile (Eng)'!L40 -> 0 | M40: =+'[2]Maturity Profile (Eng)'!M40 -> 385 | N40: =+'[2]Maturity Profile (Eng)'!N40 -> 0 | O40: =+'[2]Maturity Profile (Eng)'!O40 -> 0 | P40: =+'[2]Maturity Profile (Eng)'!P40 -> 0 | Q40: =+'[2]Maturity Profile (Eng)'!Q40 -> 0 | ... X40: =+'[2]Maturity Profile (Eng)'!X40 -> 0 | Y40: x | Z40: PRT.GLAJ650.PER - 210031 (IBF + NYA) | AD40: ='[3]Maturity Profile (Eng)'!AD40 -> 75485 | AE40: =I40 -> 385 | AF40: =AD40-AE40 -> 75100
E41: 3) | F41: Lainnya | H41: 20139 | I41: =ROUND(SUM(J41:X41),0) -> 0 | J41: =+'[2]Maturity Profile (Eng)'!J41 -> 0 | K41: =+'[2]Maturity Profile (Eng)'!K41 -> 0 | L41: =+'[2]Maturity Profile (Eng)'!L41 -> 0 | M41: =+'[2]Maturity Profile (Eng)'!M41 -> 0 | N41: =+'[2]Maturity Profile (Eng)'!N41 -> 0 | O41: =+'[2]Maturity Profile (Eng)'!O41 -> 0 | P41: =+'[2]Maturity Profile (Eng)'!P41 -> 0 | Q41: =+'[2]Maturity Profile (Eng)'!Q41 -> 0 | ... X41: =+'[2]Maturity Profile (Eng)'!X41 -> 0
C42: 2. | D42: Kewajiban kepada Bank Indonesia | H42: 20200 | I42: =ROUND(SUM(J42:X42),0) -> 0 | J42: =+'[2]Maturity Profile (Eng)'!J42 -> 0 | K42: =+'[2]Maturity Profile (Eng)'!K42 -> 0 | L42: =+'[2]Maturity Profile (Eng)'!L42 -> 0 | M42: =+'[2]Maturity Profile (Eng)'!M42 -> 0 | N42: =+'[2]Maturity Profile (Eng)'!N42 -> 0 | O42: =+'[2]Maturity Profile (Eng)'!O42 -> 0 | P42: =+'[2]Maturity Profile (Eng)'!P42 -> 0 | Q42: =+'[2]Maturity Profile (Eng)'!Q42 -> 0 | ... X42: =+'[2]Maturity Profile (Eng)'!X42 -> 0
C43: 3. | D43: Kewajiban kepada bank lain | H43: 20300 | I43: =ROUND(SUM(J43:X43),0) -> 1354900 | J43: =+'[2]Maturity Profile (Eng)'!J43 -> 1138000 | K43: =+'[2]Maturity Profile (Eng)'!K43 -> 2900 | L43: =+'[2]Maturity Profile (Eng)'!L43 -> 47000 | M43: =+'[2]Maturity Profile (Eng)'!M43 -> 43200 | N43: =+'[2]Maturity Profile (Eng)'!N43 -> 0 | O43: =+'[2]Maturity Profile (Eng)'!O43 -> 8800 | P43: =+'[2]Maturity Profile (Eng)'!P43 -> 0 | Q43: =+'[2]Maturity Profile (Eng)'!Q43 -> 0 | ... X43: =+'[2]Maturity Profile (Eng)'!X43 -> 0 | Y43: z | Z43: PRT.GLAJ650.PER - (IBF)252001+ (IBF)253001+(IBF)220001 | AE43: ='[3]Maturity Profile (Eng)'!AE43 -> 181000 | AF43: =I43 -> 1354900 | AG43: =AE43-AF43 -> -1173900
C44: 4. | D44: Surat Berharga yang Diterbitkan | H44: 20400 | I44: =ROUND(SUM(J44:X44),0) -> 0 | J44: =+SUM(J45:J47) -> 0 | K44: =+SUM(K45:K47) -> 0 | L44: =+SUM(L45:L47) -> 0 | M44: =+SUM(M45:M47) -> 0 | N44: =+SUM(N45:N47) -> 0 | O44: =+SUM(O45:O47) -> 0 | P44: =+SUM(P45:P47) -> 0 | Q44: =+SUM(Q45:Q47) -> 0 | ... X44: =+SUM(X45:X47) -> 0
D45: a. | E45: Obligasi | H45: 20410 | I45: =ROUND(SUM(J45:X45),0) -> 0 | J45: =+'[2]Maturity Profile (Eng)'!J45 -> 0 | K45: =+'[2]Maturity Profile (Eng)'!K45 -> 0 | L45: =+'[2]Maturity Profile (Eng)'!L45 -> 0 | M45: =+'[2]Maturity Profile (Eng)'!M45 -> 0 | N45: =+'[2]Maturity Profile (Eng)'!N45 -> 0 | O45: =+'[2]Maturity Profile (Eng)'!O45 -> 0 | P45: =+'[2]Maturity Profile (Eng)'!P45 -> 0 | Q45: =+'[2]Maturity Profile (Eng)'!Q45 -> 0 | ... X45: =+'[2]Maturity Profile (Eng)'!X45 -> 0
D46: b. | E46: Subordinasi ****) | H46: 20420 | I46: =ROUND(SUM(J46:X46),0) -> 0 | J46: =+'[2]Maturity Profile (Eng)'!J46 -> 0 | K46: =+'[2]Maturity Profile (Eng)'!K46 -> 0 | L46: =+'[2]Maturity Profile (Eng)'!L46 -> 0 | M46: =+'[2]Maturity Profile (Eng)'!M46 -> 0 | N46: =+'[2]Maturity Profile (Eng)'!N46 -> 0 | O46: =+'[2]Maturity Profile (Eng)'!O46 -> 0 | P46: =+'[2]Maturity Profile (Eng)'!P46 -> 0 | Q46: =+'[2]Maturity Profile (Eng)'!Q46 -> 0 | ... X46: =+'[2]Maturity Profile (Eng)'!X46 -> 0
D47: c. | E47: Lainnya | H47: 20490 | I47: =ROUND(SUM(J47:X47),0) -> 0 | J47: =+'[2]Maturity Profile (Eng)'!J47 -> 0 | K47: =+'[2]Maturity Profile (Eng)'!K47 -> 0 | L47: =+'[2]Maturity Profile (Eng)'!L47 -> 0 | M47: =+'[2]Maturity Profile (Eng)'!M47 -> 0 | N47: =+'[2]Maturity Profile (Eng)'!N47 -> 0 | O47: =+'[2]Maturity Profile (Eng)'!O47 -> 0 | P47: =+'[2]Maturity Profile (Eng)'!P47 -> 0 | Q47: =+'[2]Maturity Profile (Eng)'!Q47 -> 0 | ... X47: =+'[2]Maturity Profile (Eng)'!X47 -> 0
C48: 5. | D48: Pinjaman yang Diterima | H48: 20500 | I48: =ROUND(SUM(J48:X48),0) -> 0 | J48: =+SUM(J49:J50) -> 0 | K48: =+SUM(K49:K50) -> 0 | L48: =+SUM(L49:L50) -> 0 | M48: =+SUM(M49:M50) -> 0 | N48: =+SUM(N49:N50) -> 0 | O48: =+SUM(O49:O50) -> 0 | P48: =+SUM(P49:P50) -> 0 | Q48: =+SUM(Q49:Q50) -> 0 | ... X48: =+SUM(X49:X50) -> 0
D49: a. | E49: Pinjaman Subordinasi ****) | H49: 20510 | I49: =ROUND(SUM(J49:X49),0) -> 0 | J49: =+'[2]Maturity Profile (Eng)'!J49 -> 0 | K49: =+'[2]Maturity Profile (Eng)'!K49 -> 0 | L49: =+'[2]Maturity Profile (Eng)'!L49 -> 0 | M49: =+'[2]Maturity Profile (Eng)'!M49 -> 0 | N49: =+'[2]Maturity Profile (Eng)'!N49 -> 0 | O49: =+'[2]Maturity Profile (Eng)'!O49 -> 0 | P49: =+'[2]Maturity Profile (Eng)'!P49 -> 0 | Q49: =+'[2]Maturity Profile (Eng)'!Q49 -> 0 | ... X49: =+'[2]Maturity Profile (Eng)'!X49 -> 0
D50: b. | E50: Lainnya | H50: 20590 | I50: =ROUND(SUM(J50:X50),0) -> 0 | J50: =+'[2]Maturity Profile (Eng)'!J50 -> 0 | K50: =+'[2]Maturity Profile (Eng)'!K50 -> 0 | L50: =+'[2]Maturity Profile (Eng)'!L50 -> 0 | M50: =+'[2]Maturity Profile (Eng)'!M50 -> 0 | N50: =+'[2]Maturity Profile (Eng)'!N50 -> 0 | O50: =+'[2]Maturity Profile (Eng)'!O50 -> 0 | P50: =+'[2]Maturity Profile (Eng)'!P50 -> 0 | Q50: =+'[2]Maturity Profile (Eng)'!Q50 -> 0 | ... X50: =+'[2]Maturity Profile (Eng)'!X50 -> 0
C51: 6. | D51: Kewajiban lainnya | H51: 20700 | I51: =ROUND(SUM(J51:X51),0) -> 0 | J51: =+SUM(J52:J53) -> 0 | K51: =+SUM(K52:K53) -> 0 | L51: =+SUM(L52:L53) -> 0 | M51: =+SUM(M52:M53) -> 0 | N51: =+SUM(N52:N53) -> 0 | O51: =+SUM(O52:O53) -> 0 | P51: =+SUM(P52:P53) -> 0 | Q51: =+SUM(Q52:Q53) -> 0 | ... X51: =+SUM(X52:X53) -> 0
D52: a. | E52: Kewajiban atas Surat Berharga yang dijual dengan janji dibeli kembali (Repo) | H52: 20710 | I52: =ROUND(SUM(J52:X52),0) -> 0 | J52: =+'[2]Maturity Profile (Eng)'!J52 -> 0 | K52: =+'[2]Maturity Profile (Eng)'!K52 -> 0 | L52: =+'[2]Maturity Profile (Eng)'!L52 -> 0 | M52: =+'[2]Maturity Profile (Eng)'!M52 -> 0 | N52: =+'[2]Maturity Profile (Eng)'!N52 -> 0 | O52: =+'[2]Maturity Profile (Eng)'!O52 -> 0 | P52: =+'[2]Maturity Profile (Eng)'!P52 -> 0 | Q52: =+'[2]Maturity Profile (Eng)'!Q52 -> 0 | ... X52: =+'[2]Maturity Profile (Eng)'!X52 -> 0
D53: b. | E53: Lainnya | H53: 20790 | I53: =ROUND(SUM(J53:X53),0) -> 0 | J53: =+'[2]Maturity Profile (Eng)'!J53 -> 0 | K53: =+'[2]Maturity Profile (Eng)'!K53 -> 0 | L53: =+'[2]Maturity Profile (Eng)'!L53 -> 0 | M53: =+'[2]Maturity Profile (Eng)'!M53 -> 0 | N53: =+'[2]Maturity Profile (Eng)'!N53 -> 0 | O53: =+'[2]Maturity Profile (Eng)'!O53 -> 0 | P53: =+'[2]Maturity Profile (Eng)'!P53 -> 0 | Q53: =+'[2]Maturity Profile (Eng)'!Q53 -> 0 | ... X53: =+'[2]Maturity Profile (Eng)'!X53 -> 0
C54: 7. | D54: Lain-lain | H54: 20600 | I54: =ROUND(SUM(J54:X54),0) -> 0 | J54: =+'[2]Maturity Profile (Eng)'!J54 -> 0 | K54: =+'[2]Maturity Profile (Eng)'!K54 -> 0 | L54: =+'[2]Maturity Profile (Eng)'!L54 -> 0 | M54: =+'[2]Maturity Profile (Eng)'!M54 -> 0 | N54: =+'[2]Maturity Profile (Eng)'!N54 -> 0 | O54: =+'[2]Maturity Profile (Eng)'!O54 -> 0 | P54: =+'[2]Maturity Profile (Eng)'!P54 -> 0 | Q54: =+'[2]Maturity Profile (Eng)'!Q54 -> 0 | ... X54: =+'[2]Maturity Profile (Eng)'!X54 -> 0
J55: =SUM(J43:L43)-SUM([4]NY!$J$43:$L$43) -> 1011700
B56: C. Selisih Aset dengan Kewajiban dalam Neraca | H56: 30000 | I56: =ROUND(SUM(J56:X56),0) -> 839076 | J56: =+J14-J34 -> 129718 | K56: =+K14-K34 -> 39318 | L56: =+L14-L34 -> -43183 | M56: =+M14-M34 -> 2066 | N56: =+N14-N34 -> 30627 | O56: =+O14-O34 -> 47975 | P56: =+P14-P34 -> 122252 | Q56: =+Q14-Q34 -> 262744 | ... X56: =+X14-X34 -> 3210
B58: II | C58: REKENING ADMINISTRATIF
B59: A. | C59: Tagihan Rekening Administratif | H59: 40000 | I59: =ROUND(SUM(J59:X59),0) -> 37991 | J59: =+J60+J66 -> 37990.588 | K59: =+K60+K66 -> 0 | L59: =+L60+L66 -> 0 | M59: =+M60+M66 -> 0 | N59: =+N60+N66 -> 0 | O59: =+O60+O66 -> 0 | P59: =+P60+P66 -> 0 | Q59: =+Q60+Q66 -> 0 | ... X59: =+X60+X66 -> 0
C60: 1. | D60: Komitmen | H60: 40100 | I60: =ROUND(SUM(J60:X60),0) -> 0 | J60: =+J61+J62+J65 -> 0 | K60: =+K61+K62+K65 -> 0 | L60: =+L61+L62+L65 -> 0 | M60: =+M61+M62+M65 -> 0 | N60: =+N61+N62+N65 -> 0 | O60: =+O61+O62+O65 -> 0 | P60: =+P61+P62+P65 -> 0 | Q60: =+Q61+Q62+Q65 -> 0 | ... X60: =+X61+X62+X65 -> 0
D61: a. | E61: Fasilitas pinjaman yang belum ditarik | H61: 40110 | I61: =ROUND(SUM(J61:X61),0) -> 0 | J61: =+'[2]Maturity Profile (Eng)'!J61 -> 0 | K61: =+'[2]Maturity Profile (Eng)'!K61 -> 0 | L61: =+'[2]Maturity Profile (Eng)'!L61 -> 0 | M61: =+'[2]Maturity Profile (Eng)'!M61 -> 0 | N61: =+'[2]Maturity Profile (Eng)'!N61 -> 0 | O61: =+'[2]Maturity Profile (Eng)'!O61 -> 0 | P61: =+'[2]Maturity Profile (Eng)'!P61 -> 0 | Q61: =+'[2]Maturity Profile (Eng)'!Q61 -> 0 | ... X61: =+'[2]Maturity Profile (Eng)'!X61 -> 0
D62: b. | E62: Posisi pembelian spot dan derivatif yang masih berjalan | H62: 40120 | I62: =ROUND(SUM(J62:X62),0) -> 0 | J62: =+J63+J64 -> 0 | K62: =+K63+K64 -> 0 | L62: =+L63+L64 -> 0 | M62: =+M63+M64 -> 0 | N62: =+N63+N64 -> 0 | O62: =+O63+O64 -> 0 | P62: =+P63+P64 -> 0 | Q62: =+Q63+Q64 -> 0 | ... X62: =+X63+X64 -> 0
E63: 1) | F63: Spot | H63: 40121 | I63: =ROUND(SUM(J63:X63),0) -> 0 | J63: 0 | K63: 0 | L63: 0 | M63: 0 | N63: 0 | O63: 0 | P63: 0 | Q63: 0 | R63: 0 | S63: 0 | T63: 0 | U63: 0 | V63: 0 | W63: 0 | X63: 0
E64: 2) | F64: Derivatif | H64: 40122 | I64: =ROUND(SUM(J64:X64),0) -> 0 | J64: =+'[2]Maturity Profile (Eng)'!J64 -> 0 | K64: =+'[2]Maturity Profile (Eng)'!K64 -> 0 | L64: =+'[2]Maturity Profile (Eng)'!L64 -> 0 | M64: =+'[2]Maturity Profile (Eng)'!M64 -> 0 | N64: =+'[2]Maturity Profile (Eng)'!N64 -> 0 | O64: =+'[2]Maturity Profile (Eng)'!O64 -> 0 | P64: =+'[2]Maturity Profile (Eng)'!P64 -> 0 | Q64: =+'[2]Maturity Profile (Eng)'!Q64 -> 0 | ... X64: =+'[2]Maturity Profile (Eng)'!X64 -> 0
D65: c. | E65: Lainnya | H65: 40190 | I65: =ROUND(SUM(J65:X65),0) -> 0 | J65: =+'[2]Maturity Profile (Eng)'!J65 -> 0 | K65: =+'[2]Maturity Profile (Eng)'!K65 -> 0 | L65: =+'[2]Maturity Profile (Eng)'!L65 -> 0 | M65: =+'[2]Maturity Profile (Eng)'!M65 -> 0 | N65: =+'[2]Maturity Profile (Eng)'!N65 -> 0 | O65: =+'[2]Maturity Profile (Eng)'!O65 -> 0 | P65: =+'[2]Maturity Profile (Eng)'!P65 -> 0 | Q65: =+'[2]Maturity Profile (Eng)'!Q65 -> 0 | ... X65: =+'[2]Maturity Profile (Eng)'!X65 -> 0
C66: 2. | D66: Kontijensi *****) | H66: 40200 | I66: =ROUND(SUM(J66:X66),0) -> 37991 | J66: =+'[2]Maturity Profile (Eng)'!J66 -> 37990.588 | K66: =+'[2]Maturity Profile (Eng)'!K66 -> 0 | L66: =+'[2]Maturity Profile (Eng)'!L66 -> 0 | M66: =+'[2]Maturity Profile (Eng)'!M66 -> 0 | N66: =+'[2]Maturity Profile (Eng)'!N66 -> 0 | O66: =+'[2]Maturity Profile (Eng)'!O66 -> 0 | P66: =+'[2]Maturity Profile (Eng)'!P66 -> 0 | Q66: =+'[2]Maturity Profile (Eng)'!Q66 -> 0 | ... X66: =+'[2]Maturity Profile (Eng)'!X66 -> 0 | Y66: x | Z66: PRT.GLAJ650.PER - (NY)615001+615631+615632+620002+625106
AA67: =(27722440.01+515444.64)/1000 -> 28237.885
B68: B. | C68: Kewajiban Rekening Administratif | H68: 50000 | I68: =ROUND(SUM(J68:X68),0) -> 37991 | J68: =+J69+J76 -> 37990.588 | K68: =+K69+K76 -> 0 | L68: =+L69+L76 -> 0 | M68: =+M69+M76 -> 0 | N68: =+N69+N76 -> 0 | O68: =+O69+O76 -> 0 | P68: =+P69+P76 -> 0 | Q68: =+Q69+Q76 -> 0 | ... X68: =+X69+X76 -> 0
C69: 1. | D69: Komitmen | H69: 50100 | I69: =ROUND(SUM(J69:X69),0) -> 0 | J69: =+J70+J71+J72+J75 -> 0 | K69: =+K70+K71+K72+K75 -> 0 | L69: =+L70+L71+L72+L75 -> 0 | M69: =+M70+M71+M72+M75 -> 0 | N69: =+N70+N71+N72+N75 -> 0 | O69: =+O70+O71+O72+O75 -> 0 | P69: =+P70+P71+P72+P75 -> 0 | Q69: =+Q70+Q71+Q72+Q75 -> 0 | ... X69: =+X70+X71+X72+X75 -> 0
D70: a. | E70: Fasilitas kredit yang belum ditarik | H70: 50110 | I70: =ROUND(SUM(J70:X70),0) -> 0 | J70: =+'[2]Maturity Profile (Eng)'!J70 -> 0 | K70: =+'[2]Maturity Profile (Eng)'!K70 -> 0 | L70: =+'[2]Maturity Profile (Eng)'!L70 -> 0 | M70: =+'[2]Maturity Profile (Eng)'!M70 -> 0 | N70: =+'[2]Maturity Profile (Eng)'!N70 -> 0 | O70: =+'[2]Maturity Profile (Eng)'!O70 -> 0 | P70: =+'[2]Maturity Profile (Eng)'!P70 -> 0 | Q70: =+'[2]Maturity Profile (Eng)'!Q70 -> 0 | ... X70: =+'[2]Maturity Profile (Eng)'!X70 -> 0 | Z70: SOURCE Loan sheet
D71: b. | E71: Irrevocable L/C yang masih berjalan | H71: 50120 | I71: =ROUND(SUM(J71:X71),0) -> 0 | J71: =+'[2]Maturity Profile (Eng)'!J71 -> 0 | K71: =+'[2]Maturity Profile (Eng)'!K71 -> 0 | L71: =+'[2]Maturity Profile (Eng)'!L71 -> 0 | M71: =+'[2]Maturity Profile (Eng)'!M71 -> 0 | N71: =+'[2]Maturity Profile (Eng)'!N71 -> 0 | O71: =+'[2]Maturity Profile (Eng)'!O71 -> 0 | P71: =+'[2]Maturity Profile (Eng)'!P71 -> 0 | Q71: =+'[2]Maturity Profile (Eng)'!Q71 -> 0 | ... X71: =+'[2]Maturity Profile (Eng)'!X71 -> 0
D72: c. | E72: Posisi penjualan spot dan derivatif yang masih berjalan | H72: 50130 | I72: =ROUND(SUM(J72:X72),0) -> 0 | J72: =+J73+J74 -> 0 | K72: =+K73+K74 -> 0 | L72: =+L73+L74 -> 0 | M72: =+M73+M74 -> 0 | N72: =+N73+N74 -> 0 | O72: =+O73+O74 -> 0 | P72: =+P73+P74 -> 0 | Q72: =+Q73+Q74 -> 0 | ... X72: =+X73+X74 -> 0
E73: 1) | F73: Spot | H73: 50131 | I73: =ROUND(SUM(J73:X73),0) -> 0 | J73: =+'[2]Maturity Profile (Eng)'!J73 -> 0 | K73: =+'[2]Maturity Profile (Eng)'!K73 -> 0 | L73: =+'[2]Maturity Profile (Eng)'!L73 -> 0 | M73: =+'[2]Maturity Profile (Eng)'!M73 -> 0 | N73: =+'[2]Maturity Profile (Eng)'!N73 -> 0 | O73: =+'[2]Maturity Profile (Eng)'!O73 -> 0 | P73: =+'[2]Maturity Profile (Eng)'!P73 -> 0 | Q73: =+'[2]Maturity Profile (Eng)'!Q73 -> 0 | ... X73: =+'[2]Maturity Profile (Eng)'!X73 -> 0
E74: 2) | F74: Derivatif | H74: 50132 | I74: =ROUND(SUM(J74:X74),0) -> 0 | J74: =+'[2]Maturity Profile (Eng)'!J74 -> 0 | K74: =+'[2]Maturity Profile (Eng)'!K74 -> 0 | L74: =+'[2]Maturity Profile (Eng)'!L74 -> 0 | M74: =+'[2]Maturity Profile (Eng)'!M74 -> 0 | N74: =+'[2]Maturity Profile (Eng)'!N74 -> 0 | O74: =+'[2]Maturity Profile (Eng)'!O74 -> 0 | P74: =+'[2]Maturity Profile (Eng)'!P74 -> 0 | Q74: =+'[2]Maturity Profile (Eng)'!Q74 -> 0 | ... X74: =+'[2]Maturity Profile (Eng)'!X74 -> 0
D75: d. | E75: Lainnya | H75: 50190 | I75: =ROUND(SUM(J75:X75),0) -> 0 | J75: =+'[2]Maturity Profile (Eng)'!J75 -> 0 | K75: =+'[2]Maturity Profile (Eng)'!K75 -> 0 | L75: =+'[2]Maturity Profile (Eng)'!L75 -> 0 | M75: =+'[2]Maturity Profile (Eng)'!M75 -> 0 | N75: =+'[2]Maturity Profile (Eng)'!N75 -> 0 | O75: =+'[2]Maturity Profile (Eng)'!O75 -> 0 | P75: =+'[2]Maturity Profile (Eng)'!P75 -> 0 | Q75: =+'[2]Maturity Profile (Eng)'!Q75 -> 0 | ... X75: =+'[2]Maturity Profile (Eng)'!X75 -> 0
C76: 2. | D76: Kontijensi ******) | H76: 50200 | I76: =ROUND(SUM(J76:X76),0) -> 37991 | J76: =+'[2]Maturity Profile (Eng)'!J76 -> 37990.588 | K76: =+'[2]Maturity Profile (Eng)'!K76 -> 0 | L76: =+'[2]Maturity Profile (Eng)'!L76 -> 0 | M76: =+'[2]Maturity Profile (Eng)'!M76 -> 0 | N76: =+'[2]Maturity Profile (Eng)'!N76 -> 0 | O76: =+'[2]Maturity Profile (Eng)'!O76 -> 0 | P76: =+'[2]Maturity Profile (Eng)'!P76 -> 0 | Q76: =+'[2]Maturity Profile (Eng)'!Q76 -> 0 | ... X76: =+'[2]Maturity Profile (Eng)'!X76 -> 0 | Y76: x | Z76: PRT.GLAJ650.PER -(NY) 715001+715631+715632+720002+725106 | AF76: =(27722440.01+515444.64)/1000 -> 28237.885
B78: C. Selisih Tagihan dan Kewajiban dalam Rekening Administratif | H78: 60000 | I78: =ROUND(SUM(J78:X78),0) -> 0 | J78: =+J59-J68 -> 0 | K78: =+K59-K68 -> 0 | L78: =+L59-L68 -> 0 | M78: =+M59-M68 -> 0 | N78: =+N59-N68 -> 0 | O78: =+O59-O68 -> 0 | P78: =+P59-P68 -> 0 | Q78: =+Q59-Q68 -> 0 | ... X78: =+X59-X68 -> 0
B80: Selisih [(IA-IB)+(IIA-IIB)] | H80: 70000 | I80: 0 | J80: =+J56+J78 -> 129718 | K80: =+K56+K78 -> 39318 | L80: =+L56+L78 -> -43183 | M80: =+M56+M78 -> 2066 | N80: =+N56+N78 -> 30627 | O80: =+O56+O78 -> 47975 | P80: =+P56+P78 -> 122252 | Q80: =+Q56+Q78 -> 262744 | ... X80: =+X56+X78 -> 3210
B82: Selisih Kumulatif | H82: 80000 | I82: =+I80 -> 0 | J82: =+I82+J80 -> 129718 | K82: =+J82+K80 -> 169036 | L82: =+K82+L80 -> 125853 | M82: =+L82+M80 -> 127919 | N82: =+M82+N80 -> 158546 | O82: =+N82+O80 -> 206521 | P82: =+O82+P80 -> 328773 | Q82: =+P82+Q80 -> 591517 | ... X82: =+W82+X80 -> 839076
C85: *) | D85: Angka-angka berdasarkan jatuh tempo sesuai dengan kontrak untuk yang memiliki jatuh tempo kontraktual dan/atau estimasi dengan menggunakan berbagai asumsi untuk yang tidak memiliki jatuh tempo kontraktual | U85: PT Bank Negara Indonesia (Persero) Tbk.
C86: **) | D86: Termasuk Surat Berharga yang dijual dengan janji dibeli kembali (Repo)
C87: ***) | D87: Diisi berdasarkan perkiraan diperoleh pembayaran atas kredit yang berdasarkan kontrak sudah jatuh tempo
C88: ****) | D88: Termasuk yang diperhitungkan dalam KPMM dan dilaporkan di LBU pada pos Modal Pinjaman
C89: *****) | D89: Yang diperkirakan akan mempengaruhi arus kas (menjadi tagihan)
C90: ******) | D90: Yang diperkirakan akan mempengaruhi arus kas (menjadi kewajiban)
C92: catatan: Core Giro non bank berdasarkan data historis selama Dua (2) tahun.
B98: Catatan:
B99: ¨ | C99: Pos-pos dalam maturity profile diisi sesuai pembukuan Bank Pelapor berdasarkan sisa waktu sampai dengan jatuh tempo sesuai kontrak untuk pos neraca dan rekening administratif yang memiliki jatuh tempo kontraktual dan/ atau asumsi utk pos neraca dan rekening administratif yang tidak memiliki jatuh tempo kontraktual (non maturity items)
B103: ¨ | C103: Yang dimasukkan dalam pos-pos neraca adalah hanya pos-pos dengan karakteristik memiliki arus kas masuk / atau arus kas keluar, sehingga tidak seluruh pos di neraca di masukkan dalam laporan ini. Contoh pos neraca yang tidak dimasukkan dalam laporan ini antara lain asset tetap, AYDA, properti terbengkalai, penyertaan, dan modal
B108: ¨ | C108: Sebagai kontrol, agar sesuai dengan neraca (balance antara asset & liability --> Total Asset - Total Liability = 0 di kolom saldo (H)), maka pos-pos yang tidak dimasukkan ke dalam maturity profile tetap dimasukkan ke pos poin 7. Lainnya diletakkan di kolom (P).
C119: Tagihan --> Buy
C120: Kewajiban --> Sell

Sheet SEO
A2: A | B2: B | C2: C | D2: D | E2: E | F2: F | G2: G | I2: H | J2: I | K2: J | L2: K | M2: L | N2: M | O2: N
B3: Formulir 4.b.
B4: MATURITY PROFILE REPORT - BNI SEOUL Branch
B5: CONTRACTUAL BASED
B6: 46203
B7: Valuta Asing
I8: 1541.5 | J8: USD/KRW | K8: =SUM(J14:L14)+SUM(J59:L59) -> 37739 | L8: =K8-K9 -> 35212
K9: =SUM(J34:L34)+SUM(J68:L68) -> 2527 | W9: in Thousand USD
B10: Pos-Pos | H10: Sandi | I10: Saldo | J10: Time to Maturity *)
J11: up to 1 week | K11: > 1 week to 2 weeks | L11: > 2 weeks to 1 month | M11: > 1 month to 3 months | N11: > 3 months to 6 months | O11: > 6 months to 1 year | P11: > 1 y to 2 y | Q11: > 2 y to 3 y | R11: > 3 y to 4 y | S11: > 4 y to 5 y | T11: > 5 y to 7 y | U11: > 7 y to 10 y | V11: > 10 y to 15 y | W11: > 15 y to 20 y | X11: > 20 y
B13: I. | C13: NERACA
B14: A. | C14: Aset | H14: 10000 | I14: =ROUND(SUM(J14:X14),0) -> 445137 | J14: =ROUND(+J15+J16+J17+J18+J25+J28+J31,0) -> 37739 | K14: =ROUND(+K15+K16+K17+K18+K25+K28+K31,0) -> 0 | L14: =ROUND(+L15+L16+L17+L18+L25+L28+L31,0) -> 0 | M14: =ROUND(+M15+M16+M17+M18+M25+M28+M31,0) -> 35867 | N14: =ROUND(+N15+N16+N17+N18+N25+N28+N31,0) -> 29850 | O14: =ROUND(+O15+O16+O17+O18+O25+O28+O31,0) -> 32060 | P14: =ROUND(+P15+P16+P17+P18+P25+P28+P31,0) -> 40368 | Q14: =ROUND(+Q15+Q16+Q17+Q18+Q25+Q28+Q31,0) -> 74553 | ... X14: =ROUND(+X15+X16+X17+X18+X25+X28+X31,0) -> 0
C15: 1. | D15: Kas | H15: 10100 | I15: =ROUND(SUM(J15:X15),0) -> 264 | J15: =((406390234.5/$I$8)/1000) -> 263.63298
C16: 2. | D16: Penempatan pada Bank Indonesia | H16: 10200 | I16: =ROUND(SUM(J16:X16),0) -> 0
C17: 3. | D17: Penempatan pada bank lain | H17: 10300 | I17: =ROUND(SUM(J17:X17),0) -> 37605 | J17: =26475000/1000+11000000/1000 -> 37475 | K17: =0/$I$8/1000 -> 0 | L17: =0/$I$8/1000 -> 0 | M17: =+(200000000/I8/1000) -> 129.74376
C18: 4. | D18: Surat Berharga **) | H18: 10400 | I18: =ROUND(SUM(J18:X18),0) -> 169701 | J18: =+J19+J24 -> 0 | K18: =+K19+K24 -> 0 | L18: =+L19+L24 -> 0 | M18: =+M19+M24 -> 0 | N18: =+N19+N24 -> 11115 | O18: =+O19+O24 -> 13120 | P18: =+P19+P24 -> 25368 | Q18: =+Q19+Q24 -> 36650 | ... X18: =+X19+X24 -> 0
D19: a. | E19: Surat berharga korporasi | H19: 10420 | I19: =ROUND(SUM(J19:X19),0) -> 2000 | J19: =+SUM(J20:J23) -> 0 | K19: =+SUM(K20:K23) -> 0 | L19: =+SUM(L20:L23) -> 0 | M19: =+SUM(M20:M23) -> 0 | N19: =+SUM(N20:N23) -> 0 | O19: =+SUM(O20:O23) -> 0 | P19: =+SUM(P20:P23) -> 0 | Q19: =+SUM(Q20:Q23) -> 0 | ... X19: =+SUM(X20:X23) -> 0
E20: 1) | F20: diperdagangkan | H20: 10421 | I20: =ROUND(SUM(J20:X20),0) -> 0
E21: 2) | F21: tersedia untuk dijual | H21: 10422 | I21: =ROUND(SUM(J21:X21),0) -> 0
E22: 3) | F22: dimiliki hingga jatuh tempo | H22: 10423 | I22: =ROUND(SUM(J22:X22),0) -> 2000 | J22: 0 | S22: 2000
E23: 4) | F23: pinjaman yang diberikan dan piutang | H23: 10424 | I23: =ROUND(SUM(J23:X23),0) -> 0
D24: b. | E24: Lainnya | H24: 10490 | I24: =ROUND(SUM(J24:X24),0) -> 167701 | J24: 0 | K24: 0 | L24: 0 | M24: 0 | N24: 11115 | O24: 13120 | P24: 25368 | Q24: 36650 | R24: 31022 | S24: 34608 | T24: 15818 | U24: 0
C25: 5. | D25: Kredit Yang Diberikan | H25: 10500 | I25: =ROUND(SUM(J25:X25),0) -> 237567 | J25: =+SUM(J26:J27) -> 0 | K25: =+SUM(K26:K27) -> 0 | L25: =+SUM(L26:L27) -> 0 | M25: =+SUM(M26:M27) -> 35736.968 | N25: =+SUM(N26:N27) -> 18735.02 | O25: =+SUM(O26:O27) -> 18940 | P25: =+SUM(P26:P27) -> 15000 | Q25: =+SUM(Q26:Q27) -> 37903.317 | ... X25: =+SUM(X26:X27) -> 0
D26: a. | E26: belum jatuh tempo | H26: 10510 | I26: =ROUND(SUM(J26:X26),0) -> 237567 | J26: 0 | K26: 0 | L26: 0 | M26: 35736.968 | N26: 18735.02 | O26: 18940 | P26: 15000 | Q26: 37903.317 | R26: 51267.07 | S26: 15000 | T26: 1850 | U26: 43135.09
D27: b. | E27: sudah jatuh tempo ***) | H27: 10520 | I27: =ROUND(SUM(J27:X27),0) -> 0
C28: 6. | D28: Tagihan lainnya | H28: 10700 | I28: =ROUND(SUM(J28:X28),0) -> 0 | J28: =+SUM(J29:J30) -> 0 | K28: =+SUM(K29:K30) -> 0 | L28: =+SUM(L29:L30) -> 0 | M28: =+SUM(M29:M30) -> 0 | N28: =+SUM(N29:N30) -> 0 | O28: =+SUM(O29:O30) -> 0 | P28: =+SUM(P29:P30) -> 0 | Q28: =+SUM(Q29:Q30) -> 0 | ... X28: =+SUM(X29:X30) -> 0
D29: a. | E29: Tagihan atas Surat Berharga yang dibeli dengan janji dijual kembali (Reverse Repo) | H29: 10710 | I29: =ROUND(SUM(J29:X29),0) -> 0
D30: b. | E30: Lainnya | H30: 10790 | I30: =ROUND(SUM(J30:X30),0) -> 0
C31: 7. | D31: Lain-lain | H31: 10600 | I31: =ROUND(SUM(J31:X31),0) -> 0 | J31: 0 | K31: 0 | L31: 0 | M31: 0 | N31: 0 | O31: 0 | P31: 0 | Q31: 0 | R31: 0 | S31: 0 | T31: 0 | U31: 0
J32: =J17-[4]SEO!$J$17 -> 14225
B34: B. | C34: Kewajiban | H34: 20000 | I34: =ROUND(SUM(J34:X34),0) -> 2716 | J34: =ROUND(+J35+J42+J43+J44+J48+J51+J54,0) -> 2442 | K34: =ROUND(+K35+K42+K43+K44+K48+K51+K54,0) -> 0 | L34: =ROUND(+L35+L42+L43+L44+L48+L51+L54,0) -> 85 | M34: =ROUND(+M35+M42+M43+M44+M48+M51+M54,0) -> 189 | N34: =ROUND(+N35+N42+N43+N44+N48+N51+N54,0) -> 0 | O34: =ROUND(+O35+O42+O43+O44+O48+O51+O54,0) -> 0 | P34: =ROUND(+P35+P42+P43+P44+P48+P51+P54,0) -> 0 | Q34: =ROUND(+Q35+Q42+Q43+Q44+Q48+Q51+Q54,0) -> 0 | ... X34: =ROUND(+X35+X42+X43+X44+X48+X51+X54,0) -> 0
C35: 1. | D35: Dana Pihak Ketiga | H35: 20100 | I35: =ROUND(SUM(J35:X35),0) -> 2716 | J35: =+J36+J37+J38 -> 2441.8188 | K35: =+K36+K37+K38 -> 0 | L35: =+L36+L37+L38 -> 85.32334 | M35: =+M36+M37+M38 -> 189.19936 | N35: =+N36+N37+N38 -> 0 | O35: =+O36+O37+O38 -> 0 | P35: =+P36+P37+P38 -> 0 | Q35: =+Q36+Q37+Q38 -> 0 | ... X35: =+X36+X37+X38 -> 0
D36: a. | E36: Giro | H36: 20110 | I36: =ROUND(SUM(J36:X36),0) -> 1274 | J36: =+(1963126628.82/I8/1000) -> 1273.5171
D37: b. | E37: Tabungan | H37: 20120 | I37: =ROUND(SUM(J37:X37),0) -> 1137 | J37: =+(1752307580.88/I8/1000) -> 1136.7548
D38: c. | E38: Simpanan Berjangka | H38: 20130 | I38: =ROUND(SUM(J38:X38),0) -> 306 | J38: =+SUM(J39:J41) -> 31.54688 | K38: =+SUM(K39:K41) -> 0 | L38: =+SUM(L39:L41) -> 85.32334 | M38: =+SUM(M39:M41) -> 189.19936 | N38: =+SUM(N39:N41) -> 0 | O38: =+SUM(O39:O41) -> 0 | P38: =+SUM(P39:P41) -> 0 | Q38: =+SUM(Q39:Q41) -> 0 | ... X38: =+SUM(X39:X41) -> 0
E39: 1) | F39: Deposit on call | H39: 20131 | I39: =ROUND(SUM(J39:X39),0) -> 0
E40: 2) | F40: Deposito berjangka | H40: 20132 | I40: =ROUND(SUM(J40:X40),0) -> 306 | J40: 31.54688 | K40: 0 | L40: 85.32334 | M40: 189.19936 | N40: 0 | O40: 0 | P40: 0 | Q40: 0 | R40: 0 | S40: 0 | T40: 0 | U40: 0 | V40: 0
E41: 3) | F41: Lainnya | H41: 20139 | I41: =ROUND(SUM(J41:X41),0) -> 0
C42: 2. | D42: Kewajiban kepada Bank Indonesia | H42: 20200 | I42: =ROUND(SUM(J42:X42),0) -> 0
C43: 3. | D43: Kewajiban kepada bank lain | H43: 20300 | I43: =ROUND(SUM(J43:X43),0) -> 0 | J43: 0 | K43: 0 | M43: 0 | Q43: 0 | R43: 0
C44: 4. | D44: Surat Berharga yang Diterbitkan | H44: 20400 | I44: =ROUND(SUM(J44:X44),0) -> 0 | J44: =+SUM(J45:J47) -> 0 | K44: =+SUM(K45:K47) -> 0 | L44: =+SUM(L45:L47) -> 0 | M44: =+SUM(M45:M47) -> 0 | N44: =+SUM(N45:N47) -> 0 | O44: =+SUM(O45:O47) -> 0 | P44: =+SUM(P45:P47) -> 0 | Q44: =+SUM(Q45:Q47) -> 0 | ... X44: =+SUM(X45:X47) -> 0
D45: a. | E45: Obligasi | H45: 20410 | I45: =ROUND(SUM(J45:X45),0) -> 0
D46: b. | E46: Subordinasi ****) | H46: 20420 | I46: =ROUND(SUM(J46:X46),0) -> 0
D47: c. | E47: Lainnya | H47: 20490 | I47: =ROUND(SUM(J47:X47),0) -> 0
C48: 5. | D48: Pinjaman yang Diterima | H48: 20500 | I48: =ROUND(SUM(J48:X48),0) -> 0 | J48: =+SUM(J49:J50) -> 0 | K48: =+SUM(K49:K50) -> 0 | L48: =+SUM(L49:L50) -> 0 | M48: =+SUM(M49:M50) -> 0 | N48: =+SUM(N49:N50) -> 0 | O48: =+SUM(O49:O50) -> 0 | P48: =+SUM(P49:P50) -> 0 | Q48: =+SUM(Q49:Q50) -> 0 | ... X48: =+SUM(X49:X50) -> 0
D49: a. | E49: Pinjaman Subordinasi ****) | H49: 20510 | I49: =ROUND(SUM(J49:X49),0) -> 0
D50: b. | E50: Lainnya | H50: 20590 | I50: =ROUND(SUM(J50:X50),0) -> 0
C51: 6. | D51: Kewajiban lainnya | H51: 20700 | I51: =ROUND(SUM(J51:X51),0) -> 0 | J51: =+SUM(J52:J53) -> 0 | K51: =+SUM(K52:K53) -> 0 | L51: =+SUM(L52:L53) -> 0 | M51: =+SUM(M52:M53) -> 0 | N51: =+SUM(N52:N53) -> 0 | O51: =+SUM(O52:O53) -> 0 | P51: =+SUM(P52:P53) -> 0 | Q51: =+SUM(Q52:Q53) -> 0 | ... X51: =+SUM(X52:X53) -> 0
D52: a. | E52: Kewajiban atas Surat Berharga yang dijual dengan janji dibeli kembali (Repo) | H52: 20710 | I52: =ROUND(SUM(J52:X52),0) -> 0
D53: b. | E53: Lainnya | H53: 20790 | I53: =ROUND(SUM(J53:X53),0) -> 0
C54: 7. | D54: Lain-lain | H54: 20600 | I54: =ROUND(SUM(J54:X54),0) -> 0
B56: C. Selisih Aset dengan Kewajiban dalam Neraca | H56: 30000 | I56: =ROUND(SUM(J56:X56),0) -> 442421 | J56: =+J14-J34 -> 35297 | K56: =+K14-K34 -> 0 | L56: =+L14-L34 -> -85 | M56: =+M14-M34 -> 35678 | N56: =+N14-N34 -> 29850 | O56: =+O14-O34 -> 32060 | P56: =+P14-P34 -> 40368 | Q56: =+Q14-Q34 -> 74553 | ... X56: =+X14-X34 -> 0
B58: II | C58: REKENING ADMINISTRATIF
B59: A. | C59: Tagihan Rekening Administratif | H59: 40000 | I59: =ROUND(SUM(J59:X59),0) -> 0 | J59: =+J60+J66 -> 0 | K59: =+K60+K66 -> 0 | L59: =+L60+L66 -> 0 | M59: =+M60+M66 -> 0 | N59: =+N60+N66 -> 0 | O59: =+O60+O66 -> 0 | P59: =+P60+P66 -> 0 | Q59: =+Q60+Q66 -> 0 | ... X59: =+X60+X66 -> 0
C60: 1. | D60: Komitmen | H60: 40100 | I60: =ROUND(SUM(J60:X60),0) -> 0 | J60: =+J61+J62+J65 -> 0 | K60: =+K61+K62+K65 -> 0 | L60: =+L61+L62+L65 -> 0 | M60: =+M61+M62+M65 -> 0 | N60: =+N61+N62+N65 -> 0 | O60: =+O61+O62+O65 -> 0 | P60: =+P61+P62+P65 -> 0 | Q60: =+Q61+Q62+Q65 -> 0 | ... X60: =+X61+X62+X65 -> 0
D61: a. | E61: Fasilitas pinjaman yang belum ditarik | H61: 40110 | I61: =ROUND(SUM(J61:X61),0) -> 0
D62: b. | E62: Posisi pembelian spot dan derivatif yang masih berjalan | H62: 40120 | I62: =ROUND(SUM(J62:X62),0) -> 0 | J62: =+J63+J64 -> 0 | K62: =+K63+K64 -> 0 | L62: =+L63+L64 -> 0 | M62: =+M63+M64 -> 0 | N62: =+N63+N64 -> 0 | O62: =+O63+O64 -> 0 | P62: =+P63+P64 -> 0 | Q62: =+Q63+Q64 -> 0 | ... X62: =+X63+X64 -> 0
E63: 1) | F63: Spot | H63: 40121 | I63: =ROUND(SUM(J63:X63),0) -> 0
E64: 2) | F64: Derivatif | H64: 40122 | I64: =ROUND(SUM(J64:X64),0) -> 0
D65: c. | E65: Lainnya | H65: 40190 | I65: =ROUND(SUM(J65:X65),0) -> 0
C66: 2. | D66: Kontijensi *****) | H66: 40200 | I66: =ROUND(SUM(J66:X66),0) -> 0
B68: B. | C68: Kewajiban Rekening Administratif | H68: 50000 | I68: =ROUND(SUM(J68:X68),0) -> 0 | J68: =+J69+J76 -> 0 | K68: =+K69+K76 -> 0 | L68: =+L69+L76 -> 0 | M68: =+M69+M76 -> 0 | N68: =+N69+N76 -> 0 | O68: =+O69+O76 -> 0 | P68: =+P69+P76 -> 0 | Q68: =+Q69+Q76 -> 0 | ... X68: =+X69+X76 -> 0
C69: 1. | D69: Komitmen | H69: 50100 | I69: =ROUND(SUM(J69:X69),0) -> 0 | J69: =+J70+J71+J72+J75 -> 0 | K69: =+K70+K71+K72+K75 -> 0 | L69: =+L70+L71+L72+L75 -> 0 | M69: =+M70+M71+M72+M75 -> 0 | N69: =+N70+N71+N72+N75 -> 0 | O69: =+O70+O71+O72+O75 -> 0 | P69: =+P70+P71+P72+P75 -> 0 | Q69: =+Q70+Q71+Q72+Q75 -> 0 | ... X69: =+X70+X71+X72+X75 -> 0
D70: a. | E70: Fasilitas kredit yang belum ditarik | H70: 50110 | I70: =ROUND(SUM(J70:X70),0) -> 0
D71: b. | E71: Irrevocable L/C yang masih berjalan | H71: 50120 | I71: =ROUND(SUM(J71:X71),0) -> 0
D72: c. | E72: Posisi penjualan spot dan derivatif yang masih berjalan | H72: 50130 | I72: =ROUND(SUM(J72:X72),0) -> 0 | J72: =+J73+J74 -> 0 | K72: =+K73+K74 -> 0 | L72: =+L73+L74 -> 0 | M72: =+M73+M74 -> 0 | N72: =+N73+N74 -> 0 | O72: =+O73+O74 -> 0 | P72: =+P73+P74 -> 0 | Q72: =+Q73+Q74 -> 0 | ... X72: =+X73+X74 -> 0
E73: 1) | F73: Spot | H73: 50131 | I73: =ROUND(SUM(J73:X73),0) -> 0
E74: 2) | F74: Derivatif | H74: 50132 | I74: =ROUND(SUM(J74:X74),0) -> 0
D75: d. | E75: Lainnya | H75: 50190 | I75: =ROUND(SUM(J75:X75),0) -> 0
C76: 2. | D76: Kontijensi ******) | H76: 50200 | I76: =ROUND(SUM(J76:X76),0) -> 0
B78: C. Selisih Tagihan dan Kewajiban dalam Rekening Administratif | H78: 60000 | I78: =ROUND(SUM(J78:X78),0) -> 0 | J78: =+J59-J68 -> 0 | K78: =+K59-K68 -> 0 | L78: =+L59-L68 -> 0 | M78: =+M59-M68 -> 0 | N78: =+N59-N68 -> 0 | O78: =+O59-O68 -> 0 | P78: =+P59-P68 -> 0 | Q78: =+Q59-Q68 -> 0 | ... X78: =+X59-X68 -> 0
B80: Selisih [(IA-IB)+(IIA-IIB)] | H80: 70000 | I80: 0 | J80: =+J56+J78 -> 35297 | K80: =+K56+K78 -> 0 | L80: =+L56+L78 -> -85 | M80: =+M56+M78 -> 35678 | N80: =+N56+N78 -> 29850 | O80: =+O56+O78 -> 32060 | P80: =+P56+P78 -> 40368 | Q80: =+Q56+Q78 -> 74553 | ... X80: =+X56+X78 -> 0
B82: Selisih Kumulatif | H82: 80000 | I82: =+I80 -> 0 | J82: =+I82+J80 -> 35297 | K82: =+J82+K80 -> 35297 | L82: =+K82+L80 -> 35212 | M82: =+L82+M80 -> 70890 | N82: =+M82+N80 -> 100740 | O82: =+N82+O80 -> 132800 | P82: =+O82+P80 -> 173168 | Q82: =+P82+Q80 -> 247721 | ... X82: =+W82+X80 -> 442421
C85: *) | D85: Angka-angka berdasarkan jatuh tempo sesuai dengan kontrak untuk yang memiliki jatuh tempo kontraktual dan/atau estimasi dengan menggunakan berbagai asumsi untuk yang tidak memiliki jatuh tempo kontraktual | U85: PT Bank Negara Indonesia (Persero) Tbk.
C86: **) | D86: Termasuk Surat Berharga yang dijual dengan janji dibeli kembali (Repo)
C87: ***) | D87: Diisi berdasarkan perkiraan diperoleh pembayaran atas kredit yang berdasarkan kontrak sudah jatuh tempo
C88: ****) | D88: Termasuk yang diperhitungkan dalam KPMM dan dilaporkan di LBU pada pos Modal Pinjaman
C89: *****) | D89: Yang diperkirakan akan mempengaruhi arus kas (menjadi tagihan)
C90: ******) | D90: Yang diperkirakan akan mempengaruhi arus kas (menjadi kewajiban)
C92: catatan: Core Giro non bank berdasarkan data historis selama Dua (2) tahun.
B98: Catatan:
B99: ¨ | C99: Pos-pos dalam maturity profile diisi sesuai pembukuan Bank Pelapor berdasarkan sisa waktu sampai dengan jatuh tempo sesuai kontrak untuk pos neraca dan rekening administratif yang memiliki jatuh tempo kontraktual dan/ atau asumsi utk pos neraca dan rekening administratif yang tidak memiliki jatuh tempo kontraktual (non maturity items)
B103: ¨ | C103: Yang dimasukkan dalam pos-pos neraca adalah hanya pos-pos dengan karakteristik memiliki arus kas masuk / atau arus kas keluar, sehingga tidak seluruh pos di neraca di masukkan dalam laporan ini. Contoh pos neraca yang tidak dimasukkan dalam laporan ini antara lain asset tetap, AYDA, properti terbengkalai, penyertaan, dan modal
B108: ¨ | C108: Sebagai kontrol, agar sesuai dengan neraca (balance antara asset & liability --> Total Asset - Total Liability = 0 di kolom saldo (H)), maka pos-pos yang tidak dimasukkan ke dalam maturity profile tetap dimasukkan ke pos poin 7. Lainnya diletakkan di kolom (P).
C119: Tagihan --> Buy
C120: Kewajiban --> Sell

Sheet SG
A3: A | B3: B | C3: C | D3: D | E3: E | F3: F | G3: G | I3: H | J3: I | K3: J | L3: K | M3: L | N3: M | O3: N
B4: Formulir 4.b.
B5: MATURITY PROFILE REPORT - BNI SINGAPORE BRANCH
B6: CONTRACTUAL BASED
B7: 46203
B8: Valuta Asing | M8: Aset | N8: =SUM(J16:L16)+SUM(J61:L61) -> 490287 | O8: =N8-N9 -> 58469
M9: Kewajiban | N9: =SUM(J36:L36)+SUM(J70:L70)-N10 -> 431818
M10: rollover borrow HO | N10: 118000 | W10: in Thousand USD
B11: Pos-Pos | H11: Sandi | I11: Saldo | J11: \
J12: up to 1 week | K12: > 1 week to 2 weeks | L12: > 2 weeks to 1 month | M12: > 1 month to 3 months | N12: > 3 months to 6 months | O12: > 6 months to 1 year | P12: > 1 y to 2 y | Q12: > 2 y to 3 y | R12: > 3 y to 4 y | S12: > 4 y to 5 y | T12: > 5 y to 7 y | U12: > 7 y to 10 y | V12: > 10 y to 15 y | W12: > 15 y to 20 y | X12: > 20 y
J14: =B7+7 -> 46210 | K14: =B7+14 -> 46217 | L14: 15 Jul - 31 Jul | M14: Aug - Sep 26 | N14: Oct - Dec 26 | O14: Jan 27 - Jun 27 | P14: Jul 27 - Jun 28 | Q14: Jul 28 - Jun 29 | R14: Jul 29 - Jun 30 | S14: Jul 30 - Jun 31 | T14: Jul 31 - Jun 33 | U14: Jul 33 - Jun 36 | V14: Jul 36 - Jun 41 | W14: Jul 41 - Jun 46 | X14: > Jun 46
B15: I. | C15: NERACA
B16: A. | C16: Aset | H16: 10000 | I16: =ROUND(SUM(J16:X16),0) -> 1900794 | J16: =ROUND(+J17+J18+J19+J20+J27+J30+J33,0) -> 318616 | K16: =ROUND(+K17+K18+K19+K20+K27+K30+K33,0) -> 34599 | L16: =ROUND(+L17+L18+L19+L20+L27+L30+L33,0) -> 17072 | M16: =ROUND(+M17+M18+M19+M26+M27+M30+M33,0) -> 110939 | N16: =ROUND(+N17+N18+N19+N26+N27+N30+N33,0) -> 107407 | O16: =ROUND(+O17+O18+O19+O26+O27+O30+O33,0) -> 92732 | P16: =ROUND(+P17+P18+P19+P26+P27+P30+P33,0) -> 427856 | Q16: =ROUND(+Q17+Q18+Q19+Q26+Q27+Q30+Q33,0) -> 211102 | R16: =ROUND(+R17+R18+R19+R26+R27+R30+R33,0) -> 282928 | S16: =ROUND(+S17+S18+S19+S26+S27+S30+S33,0) -> 169654 | T16: =ROUND(+T17+T18+T19+T26+T27+T30+T33,0) -> 127889 | ... X16: =ROUND(+X17+X18+X19+X26+X27+X30+X33,0) -> 0
C17: 1. | D17: Kas | H17: 10100 | I17: =ROUND(SUM(J17:X17),0) -> 192339 | J17: 192338.56 | K17: 0 | L17: 0 | M17: 0 | N17: 0 | O17: 0 | P17: 0 | Q17: 0 | R17: 0 | S17: 0 | T17: 0 | U17: 0 | V17: 0 | W17: 0 | X17: 0 | Y17: 1011+1012+1013
C18: 2. | D18: Penempatan pada Bank Indonesia | H18: 10200 | I18: =ROUND(SUM(J18:X18),0) -> 0 | K18: 0
C19: 3. | D19: Penempatan pada bank lain | H19: 10300 | I19: =ROUND(SUM(J19:X19),0) -> 250000 | J19: 100000 | S19: 150000
C20: 4. | D20: Surat Berharga **) | H20: 10400 | I20: =ROUND(SUM(J20:X20),0) -> 241831 | J20: =SUM(J21:J26) -> 0 | K20: =SUM(K21:K26) -> 0 | L20: =SUM(L21:L26) -> 0 | M20: =SUM(M21:M26) -> 0 | N20: =SUM(N21:N26) -> 9992 | O20: =SUM(O21:O26) -> 74160.9 | P20: =SUM(P21:P26) -> 54820.074 | Q20: =SUM(Q21:Q26) -> 32262.004 | ... X20: =SUM(X21:X26) -> 0
D21: a. | E21: Surat berharga korporasi | H21: 10420 | I21: =ROUND(SUM(J21:X21),0) -> 0 | J21: =J23 -> 0 | K21: =K23 -> 0 | L21: =L23 -> 0 | M21: =M23 -> 0 | N21: =N23 -> 0 | O21: =O23 -> 0 | P21: =P23 -> 0 | Q21: =Q23 -> 0 | ... X21: =X23 -> 0
E22: 1) | F22: diperdagangkan | H22: 10421 | I22: =ROUND(SUM(J22:X22),0) -> 0 | L22: 0 | M22: 0 | U22: 0
E23: 2) | F23: tersedia untuk dijual | H23: 10422 | I23: =ROUND(SUM(J23:X23),0) -> 0 | J23: 0 | K23: 0 | L23: 0 | M23: 0 | N23: 0 | O23: 0 | P23: 0 | Q23: 0 | R23: 0 | S23: 0 | T23: 0 | U23: 0 | V23: 0 | W23: 0 | X23: 0
E24: 3) | F24: dimiliki hingga jatuh tempo | H24: 10423 | I24: =ROUND(SUM(J24:X24),0) -> 0 | P24: 0 | T24: .
E25: 4) | F25: pinjaman yang diberikan dan piutang | H25: 10424 | I25: 0 | P25: 0 | Z25: 2195
D26: b. | E26: Lainnya | H26: 10490 | I26: =SUM(J26:X26) -> 241830.78 | N26: 9992 | O26: 74160.9 | P26: 54820.074 | Q26: 32262.004 | R26: 46177.678 | S26: 19654.45 | T26: 4763.67
C27: 5. | D27: Kredit Yang Diberikan | H27: 10500 | I27: =ROUND(SUM(J27:X27),0) -> 1201171 | J27: =+SUM(J28:J29) -> 10822.839 | K27: =K29+K28 -> 34599.409 | L27: =+SUM(L28:L29) -> 17071.839 | M27: =+SUM(M28:M29) -> 110938.54 | N27: =+SUM(N28:N29) -> 97415.245 | O27: =+SUM(O28:O29) -> 18571.424 | P27: =+SUM(P28:P29) -> 373035.95 | Q27: =+SUM(Q28:Q29) -> 178840.43 | R27: =+SUM(R28:R29) -> 236750.18 | S27: =+SUM(S28:S29) -> 0 | ... X27: =+SUM(X28:X29) -> 0
D28: a. | E28: belum jatuh tempo | H28: 10510 | I28: =ROUND(SUM(J28:X28),0) -> 1201171 | J28: 10822.839 | K28: 34599.409 | L28: 17071.839 | M28: 110938.54 | N28: 97415.245 | O28: 18571.424 | P28: 373035.95 | Q28: 178840.43 | R28: 236750.18 | S28: 0 | T28: 123125 | U28: 0 | V28: 0 | W28: 0 | X28: 0 | Y28: 0
D29: b. | E29: sudah jatuh tempo ***) | H29: 10520 | I29: =ROUND(SUM(J29:X29),0) -> 0 | U29: 0
C30: 6. | D30: Tagihan lainnya | H30: 10700 | I30: =ROUND(SUM(J30:X30),0) -> 0 | J30: =+SUM(J31:J32) -> 0 | K30: =+SUM(K31:K32) -> 0 | L30: =+L31+L32 -> 0 | M30: =+SUM(M31:M32) -> 0 | N30: =+SUM(N31:N32) -> 0 | O30: =+SUM(O31:O32) -> 0 | P30: =+SUM(P31:P32) -> 0 | Q30: =+SUM(Q31:Q32) -> 0 | R30: =+SUM(R31:R32) -> 0 | S30: =+SUM(S31:S32) -> 0 | T30: =+SUM(T31:T32) -> 0 | ... X30: =+SUM(X31:X32) -> 0
D31: a. | E31: Tagihan atas Surat Berharga yang dibeli dengan janji dijual kembali (Reverse Repo) | H31: 10710 | I31: =ROUND(SUM(J31:X31),0) -> 0
D32: b. | E32: Lainnya | H32: 10790 | I32: =ROUND(SUM(J32:X32),0) -> 0 | L32: 0 | M32: 0 | N32: 0 | O32: 0 | Q32: 0 | Y32: 1464+1466+1468
C33: 7. | D33: Lain-lain | H33: 10600 | I33: =ROUND(SUM(J33:X33),0) -> 15454 | J33: =(10041637.29+5412463.62)/1000 -> 15454.101 | Y33: 1075+1157+2468+2143+2153+2157+2253+2272+2281+2282+2401+2441+2451+2453+2462
J35: =J38-[4]SG!$J$38 -> 11934.748 | K35: =SUM(J40:L40)-SUM([4]SG!$J$40:$L$40) -> 48960.12
B36: B. | C36: Kewajiban | H36: 20000 | I36: =ROUND(SUM(J36:X36),0) -> 1856176 | J36: =ROUND(+J37+J44+J45+J46+J50+J53+J56,0) -> 231708 | K36: =ROUND(+K37+K44+K45+K46+K50+K53+K56,0) -> 159352 | L36: =ROUND(+L37+L44+L45+L46+L50+L53+L56,0) -> 158758 | M36: =ROUND(+M37+M44+M45+M46+M50+M53+M56,0) -> 244121 | N36: =ROUND(+N37+N44+N45+N46+N50+N53+N56,0) -> 359613 | O36: =ROUND(+O37+O44+O45+O46+O50+O53+O56,0) -> 107713 | P36: =ROUND(+P37+P44+P45+P46+P50+P53+P56,0) -> 109911 | Q36: =ROUND(+Q37+Q44+Q45+Q46+Q50+Q53+Q56,0) -> 0 | ... X36: =ROUND(+X37+X44+X45+X46+X50+X53+X56,0) -> 0
C37: 1. | D37: Dana Pihak Ketiga | H37: 20100 | I37: =ROUND(SUM(J37:X37),0) -> 368853 | J37: =+J38+J39+J40 -> 208177.52 | K37: =+K38+K39+K40 -> 31351.806 | L37: =+L38+L39+L40 -> 106757.56 | M37: =+M38+M39+M40 -> 18121.298 | N37: =+N38+N39+N40 -> 1732.0461 | O37: =+O38+O39+O40 -> 2713.0471 | P37: =+P38+P39+P40 -> 0 | Q37: =+Q38+Q39+Q40 -> 0 | ... X37: =+X38+X39+X40 -> 0
D38: a. | E38: Giro | H38: 20110 | I38: =ROUND(SUM(J38:X38),0) -> 184950 | J38: =(110353979.68+63118132.77+11478338.37)/1000 -> 184950.45 | Y38: 3011+3012+3013
D39: b. | E39: Tabungan | H39: 20120 | I39: =ROUND(SUM(J39:X39),0) -> 3121 | J39: =3121434.31/1000 -> 3121.4343 | Y39: 3101+3102
D40: c. | E40: Simpanan Berjangka | H40: 20130 | I40: =ROUND(SUM(J40:X40),0) -> 180781 | J40: =J41+J42+J43 -> 20105.635 | K40: =K41+K42+K43 -> 31351.806 | L40: =L41+L42+L43 -> 106757.56 | M40: =M41+M42+M43 -> 18121.298 | N40: =N41+N42+N43 -> 1732.0461 | O40: =O41+O42+O43 -> 2713.0471 | P40: 0 | Q40: 0 | R40: =+SUM(R41:R43) -> 0 | S40: =+SUM(S41:S43) -> 0 | T40: =+SUM(T41:T43) -> 0 | U40: =+SUM(U41:U43) -> 0 | V40: =+SUM(V41:V43) -> 0 | W40: =+SUM(W41:W43) -> 0 | X40: =+SUM(X41:X43) -> 0
E41: 1) | F41: Deposit on call | H41: 20131 | I41: =SUM(J41:M41) -> 0 | L41: 0
E42: 2) | F42: Deposito berjangka | H42: 20132 | I42: =ROUND(SUM(J42:X42),0) -> 180781 | J42: 20105.635 | K42: 31351.806 | L42: 106757.56 | M42: 18121.298 | N42: 1732.0461 | O42: 2713.0471
E43: 3) | F43: Lainnya | H43: 20139 | I43: =ROUND(SUM(J43:X43),0) -> 0 | J43: 0 | K43: 0 | L43: 0 | M43: 0 | N43: 0 | O43: 0 | P43: 0
C44: 2. | D44: Kewajiban kepada Bank Indonesia | H44: 20200 | I44: =ROUND(SUM(J44:X44),0) -> 0 | J44: 0 | K44: 0 | L44: 0 | M44: 0 | N44: 0 | O44: 0 | P44: 0
C45: 3. | D45: Kewajiban kepada bank lain | H45: 20300 | I45: =ROUND(SUM(J45:X45),0) -> 1485792 | J45: 22000 | K45: 128000 | L45: 52000 | M45: 226000 | N45: 357881.13 | O45: 105000 | P45: 109910.55 | S45: 485000
C46: 4. | D46: Surat Berharga yang Diterbitkan | H46: 20400 | I46: =ROUND(SUM(J46:X46),0) -> 0 | J46: =+SUM(J47:J49) -> 0 | K46: =+SUM(K47:K49) -> 0 | L46: =+SUM(L47:L49) -> 0 | M46: 0 | N46: 0 | O46: 0 | P46: =+SUM(P47:P49) -> 0 | Q46: =+SUM(Q47:Q49) -> 0 | R46: =+SUM(R47:R49) -> 0 | S46: =+SUM(S47:S49) -> 0 | T46: =+SUM(T47:T49) -> 0 | U46: =+SUM(U47:U49) -> 0 | V46: =+SUM(V47:V49) -> 0 | W46: =+SUM(W47:W49) -> 0 | X46: =+SUM(X47:X49) -> 0
D47: a. | E47: Obligasi | H47: 20410 | I47: =ROUND(SUM(J47:X47),0) -> 0
D48: b. | E48: Subordinasi ****) | H48: 20420 | I48: =ROUND(SUM(J48:X48),0) -> 0
D49: c. | E49: Lainnya | H49: 20490 | I49: =ROUND(SUM(J49:X49),0) -> 0
C50: 5. | D50: Pinjaman yang Diterima | H50: 20500 | I50: =ROUND(SUM(J50:X50),0) -> 0 | J50: =+SUM(J51:J52) -> 0 | K50: =+SUM(K51:K52) -> 0 | L50: =+SUM(L51:L52) -> 0 | M50: =+SUM(M51:M52) -> 0 | N50: =+SUM(N51:N52) -> 0 | O50: =+SUM(O51:O52) -> 0 | P50: =+SUM(P51:P52) -> 0 | Q50: =+SUM(Q51:Q52) -> 0 | ... X50: =+SUM(X51:X52) -> 0
D51: a. | E51: Pinjaman Subordinasi ****) | H51: 20510 | I51: =ROUND(SUM(J51:X51),0) -> 0
D52: b. | E52: Lainnya | H52: 20590 | I52: =ROUND(SUM(J52:X52),0) -> 0
C53: 6. | D53: Kewajiban lainnya | H53: 20700 | I53: =ROUND(SUM(J53:X53),0) -> 0 | J53: =+SUM(J54:J55) -> 0 | K53: =+SUM(K54:K55) -> 0 | L53: =+SUM(L54:L55) -> 0 | M53: =+SUM(M54:M55) -> 0 | N53: =+SUM(N54:N55) -> 0 | O53: =+SUM(O54:O55) -> 0 | P53: =+SUM(P54:P55) -> 0 | Q53: =+SUM(Q54:Q55) -> 0 | ... X53: =+SUM(X54:X55) -> 0
D54: a. | E54: Kewajiban atas Surat Berharga yang dijual dengan janji dibeli kembali (Repo) | H54: 20710 | I54: =ROUND(SUM(J54:X54),0) -> 0
D55: b. | E55: Lainnya | H55: 20790 | I55: =ROUND(SUM(J55:X55),0) -> 0 | K55: 0 | L55: 0 | M55: 0 | O55: 0 | P55: 0
C56: 7. | D56: Lain-lain | H56: 20600 | I56: =ROUND(SUM(J56:X56),0) -> 1531 | J56: =(1465724.04+64858.17)/1000 -> 1530.5822 | X56: 0 | Y56: 4678+4806+4264+4496+4497+4481+4544+4571+4572+4504+4486+4501+4503+4669+4693
B58: C. Selisih Aset dengan Kewajiban dalam Neraca | H58: 30000 | I58: =ROUND(SUM(J58:X58),0) -> 44618 | J58: =+J16-J36 -> 86908 | K58: =+K16-K36 -> -124753 | L58: =+L16-L36 -> -141686 | M58: =+M16-M36 -> -133182 | N58: =+N16-N36 -> -252206 | O58: =+O16-O36 -> -14981 | P58: =+P16-P36 -> 317945 | Q58: =+Q16-Q36 -> 211102 | ... X58: =+X16-X36 -> 0
B60: II | C60: REKENING ADMINISTRATIF
B61: A. | C61: Tagihan Rekening Administratif | H61: 40000 | I61: =ROUND(SUM(J61:X61),0) -> 120000 | J61: =+J62+J68+J65 -> 120000 | K61: =+K62+K68 -> 0 | L61: =+L62+L68 -> 0 | M61: =+M62+M68 -> 0 | N61: =+N62+N68 -> 0 | O61: =+O62+O68 -> 0 | P61: =+P62+P68 -> 0 | Q61: =+Q62+Q68 -> 0 | R61: =+R62+R68 -> 0 | ... X61: =+X62+X68 -> 0
C62: 1. | D62: Komitmen | H62: 40100 | I62: =ROUND(SUM(J62:X62),0) -> 120000 | J62: =+J63+J64+J67 -> 120000 | K62: =+K63+K64+K67 -> 0 | L62: =+L63+L64+L67 -> 0 | M62: =+M63+M64+M67 -> 0 | N62: =+N63+N64+N67 -> 0 | O62: =+O63+O64+O67 -> 0 | P62: =+P63+P64+P67 -> 0 | Q62: =+Q63+Q64+Q67 -> 0 | ... X62: =+X63+X64+X67 -> 0
D63: a. | E63: Fasilitas pinjaman yang belum ditarik | H63: 40110 | I63: =ROUND(SUM(J63:X63),0) -> 120000 | J63: =20000+60000+40000 -> 120000
D64: b. | E64: Posisi pembelian spot dan derivatif yang masih berjalan | H64: 40120 | I64: =ROUND(SUM(J64:X64),0) -> 0 | K64: =+K65+K66 -> 0 | L64: =+L65+L66 -> 0 | M64: =+M65+M66 -> 0 | N64: =+N65+N66 -> 0 | O64: =+O65+O66 -> 0 | P64: =+P65+P66 -> 0 | Q64: =+Q65+Q66 -> 0 | R64: =+R65+R66 -> 0 | ... X64: =+X65+X66 -> 0
E65: 1) | F65: Spot | H65: 40121 | I65: =ROUND(SUM(J65:X65),0) -> 0 | Y65: 9022
E66: 2) | F66: Derivatif | H66: 40122 | I66: =ROUND(SUM(J66:X66),0) -> 0
D67: c. | E67: Lainnya | H67: 40190 | I67: =ROUND(SUM(J67:X67),0) -> 0
C68: 2. | D68: Kontijensi *****) | H68: 40200 | I68: =ROUND(SUM(J68:X68),0) -> 0 | J68: 0 | M68: 0 | N68: 0 | O68: 0
B70: B. | C70: Kewajiban Rekening Administratif | H70: 50000 | I70: =ROUND(SUM(J70:X70),0) -> 0 | J70: =+J71+J78+J75 -> 0 | K70: =+K71+K78 -> 0 | L70: =+L71+L78 -> 0 | M70: =+M71+M78 -> 0 | N70: =+N71+N78 -> 0 | O70: =+O71+O78 -> 0 | P70: =+P71+P78 -> 0 | Q70: =+Q71+Q78 -> 0 | R70: =+R71+R78 -> 0 | ... X70: =+X71+X78 -> 0
C71: 1. | D71: Komitmen | H71: 50100 | I71: =ROUND(SUM(J71:X71),0) -> 0 | J71: =+J72+J73+J74+J77 -> 0 | K71: =+K72+K73+K74+K77 -> 0 | L71: =+L72+L73+L74+L77 -> 0 | M71: =+M72+M73+M74+M77 -> 0 | N71: =+N72+N73+N74+N77 -> 0 | O71: =+O72+O73+O74+O77 -> 0 | P71: =+P72+P73+P74+P77 -> 0 | Q71: =+Q72+Q73+Q74+Q77 -> 0 | ... X71: =+X72+X73+X74+X77 -> 0
D72: a. | E72: Fasilitas kredit yang belum ditarik | H72: 50110 | I72: =ROUND(SUM(J72:X72),0) -> 0
D73: b. | E73: Irrevocable L/C yang masih berjalan | H73: 50120 | I73: =ROUND(SUM(J73:X73),0) -> 0 | L73: 0 | Y73: 9016+9117+9118+9015+9116
D74: c. | E74: Posisi penjualan spot dan derivatif yang masih berjalan | H74: 50130 | I74: =ROUND(SUM(J74:X74),0) -> 0 | K74: =+K75+K76 -> 0 | L74: =+L75+L76 -> 0 | M74: =+M75+M76 -> 0 | N74: =+N75+N76 -> 0 | O74: =+O75+O76 -> 0 | P74: =+P75+P76 -> 0 | Q74: =+Q75+Q76 -> 0 | R74: =+R75+R76 -> 0 | ... X74: =+X75+X76 -> 0
E75: 1) | F75: Spot | H75: 50131 | I75: =ROUND(SUM(J75:X75),0) -> 0 | Y75: 9023+9024
E76: 2) | F76: Derivatif | H76: 50132 | I76: =ROUND(SUM(J76:X76),0) -> 0
D77: d. | E77: Lainnya | H77: 50190 | I77: =ROUND(SUM(J77:X77),0) -> 0
C78: 2. | D78: Kontijensi ******) | H78: 50200 | I78: =ROUND(SUM(J78:X78),0) -> 0 | J78: 0 | M78: 0 | N78: 0 | O78: 0 | Y78: 9011+9032+9031
B80: C. Selisih Tagihan dan Kewajiban dalam Rekening Administratif | H80: 60000 | I80: =ROUND(SUM(J80:X80),0) -> 120000 | J80: =+J61-J70 -> 120000 | K80: =+K61-K70 -> 0 | L80: =+L61-L70 -> 0 | M80: =+M61-M70 -> 0 | N80: =+N61-N70 -> 0 | O80: =+O61-O70 -> 0 | P80: =+P61-P70 -> 0 | Q80: =+Q61-Q70 -> 0 | ... X80: =+X61-X70 -> 0
B82: Selisih [(IA-IB)+(IIA-IIB)] | H82: 70000 | I82: 0 | J82: =+J58+J80 -> 206908 | K82: =+K58+K80 -> -124753 | L82: =+L58+L80 -> -141686 | M82: =+M58+M80 -> -133182 | N82: =+N58+N80 -> -252206 | O82: =+O58+O80 -> -14981 | P82: =+P58+P80 -> 317945 | Q82: =+Q58+Q80 -> 211102 | ... X82: =+X58+X80 -> 0
B84: Selisih Kumulatif | H84: 80000 | I84: =+I82 -> 0 | J84: =+I84+J82 -> 206908 | K84: =+J84+K82 -> 82155 | L84: =+K84+L82 -> -59531 | M84: =+L84+M82 -> -192713 | N84: =+M84+N82 -> -444919 | O84: =+N84+O82 -> -459900 | P84: =+O84+P82 -> -141955 | Q84: =+P84+Q82 -> 69147 | ... X84: =+W84+X82 -> 164618
C87: *) | D87: Angka-angka berdasarkan jatuh tempo sesuai dengan kontrak untuk yang memiliki jatuh tempo kontraktual dan/atau estimasi dengan menggunakan berbagai asumsi untuk yang tidak memiliki jatuh tempo kontraktual | U87: PT Bank Negara Indonesia (Persero) Tbk.
C88: **) | D88: Termasuk Surat Berharga yang dijual dengan janji dibeli kembali (Repo)
C89: ***) | D89: Diisi berdasarkan perkiraan diperoleh pembayaran atas kredit yang berdasarkan kontrak sudah jatuh tempo
C90: ****) | D90: Termasuk yang diperhitungkan dalam KPMM dan dilaporkan di LBU pada pos Modal Pinjaman
C91: *****) | D91: Yang diperkirakan akan mempengaruhi arus kas (menjadi tagihan)
C92: ******) | D92: Yang diperkirakan akan mempengaruhi arus kas (menjadi kewajiban)
C94: catatan: Core Giro non bank berdasarkan data historis selama Dua (2) tahun.
B100: Catatan:
B101: ¨ | C101: Pos-pos dalam maturity profile diisi sesuai pembukuan Bank Pelapor berdasarkan sisa waktu sampai dengan jatuh tempo sesuai kontrak untuk pos neraca dan rekening administratif yang memiliki jatuh tempo kontraktual dan/ atau asumsi utk pos neraca dan rekening administratif yang tidak memiliki jatuh tempo kontraktual (non maturity items)
B105: ¨ | C105: Yang dimasukkan dalam pos-pos neraca adalah hanya pos-pos dengan karakteristik memiliki arus kas masuk / atau arus kas keluar, sehingga tidak seluruh pos di neraca di masukkan dalam laporan ini. Contoh pos neraca yang tidak dimasukkan dalam laporan ini antara lain asset tetap, AYDA, properti terbengkalai, penyertaan, dan modal
B110: ¨ | C110: Sebagai kontrol, agar sesuai dengan neraca (balance antara asset & liability --> Total Asset - Total Liability = 0 di kolom saldo (H)), maka pos-pos yang tidak dimasukkan ke dalam maturity profile tetap dimasukkan ke pos poin 7. Lainnya diletakkan di kolom (P).
C121: Tagihan --> Buy
C122: Kewajiban --> Sell

Sheet TKY
A2: A | B2: B | C2: C | D2: D | E2: E | F2: F | G2: G | I2: H | J2: I | K2: J | L2: K | M2: L | N2: M | O2: N
B3: Formulir 4.b.
B4: MATURITY PROFILE REPORT - BNI TOKYO Branch
B5: CONTRACTUAL BASED
B6: As of 30 June 2026
I7: Aset | J7: =(SUM(J14:L14))+(SUM(J62:L62)) -> 596768 | K7: =+J7/J8 -> 1.2518575 | L7: =J7-J8 -> 120062
I8: Kewajiban | J8: =(SUM(J36:L36))+(SUM(J71:L71))-((G89+G90+G91)/1000) -> 476706 | X8: in Thousand USD
J9: 46210 | K9: 46217 | L9: 46234 | M9: 46295 | N9: 46387 | O9: 46568 | P9: 46934 | Q9: 47299 | R9: 47664 | S9: 48029 | T9: 48760 | U9: 49856 | V9: 51682 | W9: 53508
B10: Pos-Pos | H10: Sandi | I10: Saldo | J10: Time to Maturity *)
J11: up to 1 week | K11: > 1 week to 2 weeks | L11: > 2 weeks to 1 month | M11: > 1 month to 3 months | N11: > 3 months to 6 months | O11: > 6 months to 1 year | P11: > 1 y to 2 y | Q11: > 2 y to 3 y | R11: > 3 y to 4 y | S11: > 4 y to 5 y | T11: > 5 y to 7 y | U11: > 7 y to 10 y | V11: > 10 y to 15 y | W11: > 15 y to 20 y | X11: > 20 y
B13: I. | C13: NERACA
B14: A. | C14: Aset | H14: 10000 | I14: 1021397 | J14: 505264 | K14: 0 | L14: 1504 | M14: 7810 | N14: 57021 | O14: 55616 | P14: 72615 | Q14: 169643 | R14: 16881 | S14: 10055 | T14: 44819 | U14: 77610 | V14: 2559 | W14: 0 | X14: 0
C15: 1. | D15: Kas | H15: 10100 | I15: 234 | J15: 233.93701 | K15: 0 | L15: 0 | M15: 0 | N15: 0 | O15: 0 | P15: 0 | Q15: 0 | R15: 0 | S15: 0 | T15: 0 | U15: 0 | V15: 0 | W15: 0 | X15: 0
C16: 2. | D16: Penempatan pada Bank Indonesia | H16: 10200 | I16: 0 | J16: 0 | K16: 0 | L16: 0 | M16: 0 | N16: 0 | O16: 0 | P16: 0 | Q16: 0 | R16: 0 | S16: 0 | T16: 0 | U16: 0 | V16: 0 | W16: 0 | X16: 0
C17: 3. | D17: Penempatan pada bank lain | H17: 10300 | I17: 505030 | J17: 505029.86 | K17: 0 | L17: 0 | M17: 0 | N17: 0 | O17: 0 | P17: 0 | Q17: 0 | R17: 0 | S17: 0 | T17: 0 | U17: 0 | V17: 0 | W17: 0 | X17: 0
E18: 1) | F18: Penempatan pada Bank Central setempat (BOJ) | I18: 390198.39 | J18: 390198.39
E19: 2) | F19: Penempatan pada bank lain exclude Bank Central | I19: 114831.47 | J19: 114831.47
C20: 4. | D20: Surat Berharga **) | H20: 10400 | I20: 116061 | K20: 0 | L20: 0 | M20: 0 | N20: 0 | O20: 41706.579 | P20: 19113.223 | Q20: 0 | R20: 16331.748 | S20: 9778.7724 | T20: 26571.795 | U20: 0 | V20: 2558.9009 | W20: 0 | X20: 0
D21: a. | E21: Surat berharga | H21: 10420 | I21: 116061 | J21: 0 | K21: 0 | L21: 0 | M21: 0 | N21: 0 | O21: 41706.579 | P21: 19113.223 | Q21: 0 | R21: 16331.748 | S21: 9778.7724 | T21: 26571.795 | U21: 0 | V21: 2558.9009 | W21: 0 | X21: 0
E22: 1) | F22: diperdagangkan | H22: 10421 | I22: 0 | J22: 0 | K22: 0 | L22: 0 | M22: 0 | N22: 0 | O22: 0 | P22: 0 | Q22: 0 | R22: 0 | S22: 0 | T22: 0 | U22: 0 | V22: 0 | W22: 0 | X22: 0
E23: 2) | F23: tersedia untuk dijual | H23: 10422 | I23: 78850 | J23: 0 | K23: 0 | L23: 0 | M23: 0 | N23: 0 | O23: 17540.225 | P23: 14046.013 | Q23: 0 | R23: 14357.925 | S23: 3775.2 | T23: 26571.795 | U23: 0 | V23: 2558.9009 | W23: 0 | X23: 0
E24: 3) | F24: dimiliki hingga jatuh tempo | H24: 10533 | I24: 37211 | J24: 0 | K24: 0 | L24: 0 | M24: 0 | N24: 0 | O24: 24166.354 | P24: 5067.2097 | Q24: 0 | R24: 1973.8231 | S24: 6003.5724 | T24: 0 | U24: 0 | V24: 0 | W24: 0 | X24: 0
E25: 4) | F25: pinjaman yang diberikan dan piutang | H25: 10424 | I25: 0 | J25: 0 | K25: 0 | L25: 0 | M25: 0 | N25: 0 | O25: 0 | P25: 0 | Q25: 0 | R25: 0 | S25: 0 | T25: 0 | U25: 0 | V25: 0 | W25: 0 | X25: 0
D26: b. | E26: Lainnya | H26: 10490 | I26: 0
C27: 5. | D27: Kredit Yang Diberikan | H27: 10500 | I27: 402770 | J27: 0 | K27: 0 | L27: 1503.587 | M27: 7809.6531 | N27: 57021.396 | O27: 13909.532 | P27: 56199.232 | Q27: 169643.28 | R27: 549.22735 | S27: 276.2386 | T27: 18247.468 | U27: 77609.955 | V27: 0 | W27: 0 | X27: 0
D28: a. | E28: belum jatuh tempo | H28: 10500 | I28: 402770 | J28: 0 | K28: 0 | L28: 1503.587 | M28: 7809.6531 | N28: 57021.396 | O28: 13909.532 | P28: 56199.232 | Q28: 169643.28 | R28: 549.22735 | S28: 276.2386 | T28: 18247.468 | U28: 77609.955 | V28: 0 | W28: 0 | X28: 0
D29: b. | E29: sudah jatuh tempo ***) | H29: 10520 | I29: 0
C30: 6. | D30: Tagihan lainnya | H30: 10700 | I30: 0 | J30: 0 | K30: 0 | L30: 0 | M30: 0 | N30: 0 | O30: 0 | P30: 0 | Q30: 0 | R30: 0 | S30: 0 | T30: 0 | U30: 0 | V30: 0 | W30: 0 | X30: 0
D31: a. | E31: Tagihan atas Surat Berharga yang dibeli dengan janji dijual kembali (Reverse Repo) | H31: 10710 | I31: 0 | J31: 0 | K31: 0 | L31: 0 | M31: 0 | N31: 0 | O31: 0 | P31: 0 | Q31: 0 | R31: 0 | S31: 0 | T31: 0 | U31: 0 | V31: 0 | W31: 0 | X31: 0
D32: b. | E32: Lainnya | H32: 10790 | I32: 0 | J32: 0 | K32: 0 | L32: 0 | M32: 0 | N32: 0 | O32: 0 | P32: 0 | Q32: 0 | R32: 0 | S32: 0 | T32: 0 | U32: 0 | V32: 0 | W32: 0 | X32: 0
C33: 7. | D33: Lain-lain | H33: 10600 | I33: -2698 | J33: 0 | K33: 0 | L33: 0 | M33: 0 | N33: 0 | O33: 0 | P33: -2697.6684 | Q33: 0 | R33: 0 | S33: 0 | T33: 0 | U33: 0 | V33: 0 | W33: 0 | X33: 0
J35: 46210 | K35: 46217 | L35: 46234 | M35: 46295 | N35: 46387 | O35: 46568 | P35: 46934
B36: B. | C36: Kewajiban | H36: 20000 | I36: 1021396 | J36: 467394 | K36: 0 | L36: 9312 | M36: 174203 | N36: 256175 | O36: 46329 | P36: 67982 | Q36: 0 | R36: 0 | S36: 0 | T36: 0 | U36: 0 | V36: 0 | W36: 0 | X36: 0
C37: 1. | D37: Dana Pihak Ketiga | H37: 20100 | I37: 497347 | J37: 461288.29 | K37: 0 | L37: 6224.7453 | M37: 11115.587 | N37: 0 | O37: 6369.1065 | P37: 12349.491 | Q37: 0 | R37: 0 | S37: 0 | T37: 0 | U37: 0 | V37: 0 | W37: 0 | X37: 0
D38: a. | E38: Giro | H38: 20110 | I38: 90253.11 | J38: 90253.11 | M38: 0 | N38: 0 | O38: 0 | P38: 0 | Q38: 0 | R38: 0 | S38: 0 | T38: 0 | U38: 0 | V38: 0 | W38: 0 | X38: 0
D39: b. | E39: Tabungan | H39: 20120 | I39: 371035.18 | J39: 371035.18 | K39: 0 | L39: 0 | M39: 0 | N39: 0 | O39: 0 | P39: 0 | Q39: 0 | R39: 0 | S39: 0 | T39: 0 | U39: 0 | V39: 0 | W39: 0 | X39: 0
D40: c. | E40: Simpanan Berjangka | H40: 20130 | I40: 36058.93 | J40: 0 | K40: 0 | L40: 6224.7453 | M40: 11115.587 | N40: 0 | O40: 6369.1065 | P40: 12349.491 | Q40: 0 | R40: 0 | S40: 0 | T40: 0 | U40: 0 | V40: 0 | W40: 0 | X40: 0
E41: 1) | F41: Deposit on call | H41: 20131 | I41: 0 | K41: 0 | L41: 0 | M41: 0 | N41: 0 | O41: 0 | Q41: 0 | R41: 0 | S41: 0 | T41: 0 | U41: 0 | V41: 0 | W41: 0 | X41: 0
E42: 2) | F42: Deposito berjangka | H42: 20132 | I42: 36058.93 | J42: 0 | K42: 0 | L42: 6224.7453 | M42: 11115.587 | N42: 0 | O42: 6369.1065 | P42: 12349.491 | Q42: 0 | R42: 0 | S42: 0 | T42: 0 | U42: 0 | V42: 0 | W42: 0
E43: 3) | F43: Lainnya | H43: 20139 | I43: 0 | J43: 0 | K43: 0 | L43: 0 | M43: 0 | N43: 0 | O43: 0 | P43: 0 | Q43: 0 | R43: 0 | S43: 0 | T43: 0 | U43: 0 | V43: 0 | W43: 0 | X43: 0
C44: 2. | D44: Kewajiban kepada Bank Indonesia | H44: 20200 | I44: 6106.0706 | J44: 6106.0706 | P44: 0 | Q44: 0 | R44: 0 | S44: 0 | T44: 0 | U44: 0 | V44: 0 | W44: 0 | X44: 0
C45: 3. | D45: Kewajiban kepada bank lain | H45: 20300 | I45: 490331.93 | J45: 0 | K45: 0 | L45: 3087.3726 | M45: 163087.37 | N45: 256174.75 | O45: 12349.491 | P45: 55632.944 | Q45: 0 | R45: 0 | S45: 0 | T45: 0 | U45: 0 | V45: 0 | W45: 0 | X45: 0
C46: 3. | D46: Kewajiban kepada bank Central setempat | H46: 20300 | I46: 0 | J46: 0 | K46: 0 | L46: 0 | M46: 0 | N46: 0 | O46: 0 | P46: 0 | Q46: 0 | R46: 0 | S46: 0 | T46: 0 | U46: 0 | V46: 0 | W46: 0 | X46: 0
C47: 4. | D47: Surat Berharga yang Diterbitkan | H47: 20400 | I47: 0 | J47: 0 | K47: 0 | L47: 0 | M47: 0 | N47: 0 | O47: 0 | P47: 0 | Q47: 0 | R47: 0 | S47: 0 | T47: 0 | U47: 0 | V47: 0 | W47: 0 | X47: 0
D48: a. | E48: Obligasi | H48: 20410 | I48: 0 | J48: 0 | K48: 0 | L48: 0 | M48: 0 | N48: 0 | O48: 0 | P48: 0 | Q48: 0 | R48: 0 | S48: 0 | T48: 0 | U48: 0 | V48: 0 | W48: 0 | X48: 0
D49: b. | E49: Subordinasi ****) | H49: 20420 | I49: 0 | J49: 0 | K49: 0 | L49: 0 | M49: 0 | N49: 0 | O49: 0 | P49: 0 | Q49: 0 | R49: 0 | S49: 0 | T49: 0 | U49: 0 | V49: 0 | W49: 0 | X49: 0
D50: c. | E50: Lainnya | H50: 20490 | I50: 0 | J50: 0 | K50: 0 | L50: 0 | M50: 0 | N50: 0 | O50: 0 | P50: 0 | Q50: 0 | R50: 0 | S50: 0 | T50: 0 | U50: 0 | V50: 0 | W50: 0 | X50: 0
C51: 5. | D51: Pinjaman yang Diterima | H51: 20500 | I51: 0 | J51: 0 | K51: 0 | L51: 0 | M51: 0 | N51: 0 | O51: 0 | P51: 0 | Q51: 0 | R51: 0 | S51: 0 | T51: 0 | U51: 0 | V51: 0 | W51: 0 | X51: 0
D52: a. | E52: Pinjaman Subordinasi ****) | H52: 20510 | I52: 0 | J52: 0 | K52: 0 | L52: 0 | M52: 0 | N52: 0 | O52: 0 | P52: 0 | Q52: 0 | R52: 0 | S52: 0 | T52: 0 | U52: 0 | V52: 0 | W52: 0 | X52: 0
D53: b. | E53: Lainnya | H53: 20590 | I53: 0 | J53: 0 | K53: 0 | L53: 0 | M53: 0 | N53: 0 | O53: 0 | P53: 0 | Q53: 0 | R53: 0 | S53: 0 | T53: 0 | U53: 0 | V53: 0 | W53: 0 | X53: 0
C54: 6. | D54: Kewajiban lainnya | H54: 20700 | I54: 27611 | J54: 0 | K54: 0 | L54: 0 | M54: 0 | N54: 0 | O54: 27610.797 | P54: 0 | Q54: 0 | R54: 0 | S54: 0 | T54: 0 | U54: 0 | V54: 0 | W54: 0 | X54: 0
D55: a. | E55: Kewajiban atas Surat Berharga yang dijual dengan janji dibeli kembali (Repo) | H55: 20710 | I55: 0 | J55: 0 | K55: 0 | L55: 0 | M55: 0 | N55: 0 | O55: 0 | P55: 0 | Q55: 0 | R55: 0 | S55: 0 | T55: 0 | U55: 0 | V55: 0 | W55: 0 | X55: 0
D56: b. | E56: Lainnya | H56: 20790 | I56: 27611 | K56: 0 | L56: 0 | M56: 0 | N56: 0 | O56: 27610.797 | Q56: 0 | R56: 0 | S56: 0 | T56: 0 | U56: 0 | V56: 0 | W56: 0 | X56: 0
C57: 7. | D57: Lain-lain | H57: 20600 | I57: 0 | J57: 0 | K57: 0 | L57: 0 | M57: 0 | N57: 0 | O57: 0 | P57: 0 | Q57: 0 | R57: 0 | S57: 0 | T57: 0 | U57: 0 | V57: 0 | W57: 0 | X57: 0
B59: C. Selisih Aset dengan Kewajiban dalam Neraca | H59: 30000 | J59: 37870 | K59: 0 | L59: -7808 | M59: -166393 | N59: -199154 | O59: 9287 | P59: 4633 | Q59: 169643 | R59: 16881 | S59: 10055 | T59: 44819 | U59: 77610 | V59: 2559 | W59: 0 | X59: 0
B61: II | C61: REKENING ADMINISTRATIF
B62: A. | C62: Tagihan Rekening Administratif (Receivable) | H62: 40000 | I62: 90000 | J62: 90000 | K62: 0 | L62: 0 | M62: 0 | N62: 0 | O62: 0 | P62: 0 | Q62: 0 | R62: 0 | S62: 0 | T62: 0 | U62: 0 | V62: 0 | W62: 0 | X62: 0
C63: 1. | D63: Komitmen | H63: 40100 | I63: 90000 | J63: 90000 | K63: 0 | L63: 0 | M63: 0 | N63: 0 | O63: 0 | P63: 0 | Q63: 0 | R63: 0 | S63: 0 | T63: 0 | U63: 0 | V63: 0 | W63: 0 | X63: 0
D64: a. | E64: Fasilitas pinjaman yang belum ditarik | H64: 40110 | I64: 90000 | J64: 90000 | K64: 0 | L64: 0 | M64: 0 | N64: 0 | O64: 0 | P64: 0 | Q64: 0 | R64: 0 | S64: 0 | T64: 0 | U64: 0 | V64: 0 | W64: 0 | X64: 0
D65: b. | E65: Posisi pembelian spot dan derivatif yang masih berjalan | H65: 40120 | I65: 0 | J65: 0 | K65: 0 | L65: 0 | M65: 0 | N65: 0 | O65: 0 | P65: 0 | Q65: 0 | R65: 0 | S65: 0 | T65: 0 | U65: 0 | V65: 0 | W65: 0 | X65: 0
E66: 1) | F66: Spot | H66: 40121 | I66: 0 | J66: 0 | K66: 0 | L66: 0 | M66: 0 | N66: 0 | O66: 0 | P66: 0 | Q66: 0 | R66: 0 | S66: 0 | T66: 0 | U66: 0 | V66: 0 | W66: 0 | X66: 0
E67: 2) | F67: Derivatif | H67: 40122 | I67: 0 | J67: 0 | K67: 0 | L67: 0 | M67: 0 | N67: 0 | O67: 0 | P67: 0 | Q67: 0 | R67: 0 | S67: 0 | T67: 0 | U67: 0 | V67: 0 | W67: 0 | X67: 0
D68: c. | E68: Lainnya | H68: 40190 | I68: 0 | J68: 0 | K68: 0 | L68: 0 | M68: 0 | N68: 0 | O68: 0 | P68: 0 | Q68: 0 | R68: 0 | S68: 0 | T68: 0 | U68: 0 | V68: 0 | W68: 0 | X68: 0
C69: 2. | D69: Kontijensi *****) | H69: 40200 | I69: 0 | J69: 0 | K69: 0 | L69: 0 | M69: 0 | N69: 0 | O69: 0 | P69: 0 | Q69: 0 | R69: 0 | S69: 0 | T69: 0 | U69: 0 | V69: 0 | W69: 0 | X69: 0
B71: B. | C71: Kewajiban Rekening Administratif (Payable) | H71: 50000 | I71: 0 | J71: 0 | K71: 0 | L71: 0 | M71: 0 | N71: 0 | O71: 0 | P71: 0 | Q71: 0 | R71: 0 | S71: 0 | T71: 0 | U71: 0 | V71: 0 | W71: 0 | X71: 0
C72: 1. | D72: Komitmen | H72: 50100 | I72: 0 | J72: 0 | K72: 0 | L72: 0 | M72: 0 | N72: 0 | O72: 0 | P72: 0 | Q72: 0 | R72: 0 | S72: 0 | T72: 0 | U72: 0 | V72: 0 | W72: 0 | X72: 0
D73: a. | E73: Fasilitas kredit yang belum ditarik | H73: 50110 | I73: 0 | J73: 0 | K73: 0 | L73: 0 | M73: 0 | N73: 0 | O73: 0 | P73: 0 | Q73: 0 | R73: 0 | S73: 0 | T73: 0 | U73: 0 | V73: 0 | W73: 0 | X73: 0
D74: b. | E74: Irrevocable L/C yang masih berjalan | H74: 50120 | I74: 0 | J74: 0 | K74: 0 | L74: 0 | M74: 0 | N74: 0 | O74: 0 | P74: 0 | Q74: 0 | R74: 0 | S74: 0 | T74: 0 | U74: 0 | V74: 0 | W74: 0 | X74: 0
D75: c. | E75: Posisi penjualan spot dan derivatif yang masih berjalan | H75: 50130 | I75: 0 | J75: 0 | K75: 0 | L75: 0 | M75: 0 | N75: 0 | O75: 0 | P75: 0 | Q75: 0 | R75: 0 | S75: 0 | T75: 0 | U75: 0 | V75: 0 | W75: 0 | X75: 0
E76: 1) | F76: Spot | H76: 50131 | I76: 0 | J76: 0 | K76: 0 | L76: 0 | M76: 0 | N76: 0 | O76: 0 | P76: 0 | Q76: 0 | R76: 0 | S76: 0 | T76: 0 | U76: 0 | V76: 0 | W76: 0 | X76: 0
E77: 2) | F77: Derivatif | H77: 50132 | I77: 0 | J77: 0 | K77: 0 | L77: 0 | M77: 0 | N77: 0 | O77: 0 | P77: 0 | Q77: 0 | R77: 0 | S77: 0 | T77: 0 | U77: 0 | V77: 0 | W77: 0 | X77: 0
D78: d. | E78: Lainnya | H78: 50190 | I78: 0 | J78: 0 | K78: 0 | L78: 0 | M78: 0 | N78: 0 | O78: 0 | P78: 0 | Q78: 0 | R78: 0 | S78: 0 | T78: 0 | U78: 0 | V78: 0 | W78: 0 | X78: 0
C79: 2. | D79: Kontijensi ******) | H79: 50200 | I79: 0 | J79: 0 | K79: 0 | L79: 0 | M79: 0 | N79: 0 | O79: 0 | P79: 0 | Q79: 0 | R79: 0 | S79: 0 | T79: 0 | U79: 0 | V79: 0 | W79: 0 | X79: 0
B81: C. Selisih Tagihan dan Kewajiban dalam Rekening Administratif | H81: 60000 | I81: 90000 | J81: 90000 | K81: 0 | L81: 0 | M81: 0 | N81: 0 | O81: 0 | P81: 0 | Q81: 0 | R81: 0 | S81: 0 | T81: 0 | U81: 0 | V81: 0 | W81: 0 | X81: 0
B83: Selisih [(IA-IB)+(IIA-IIB)] | H83: 70000 | I83: 90001.004 | J83: 127870 | K83: 0 | L83: -7808 | M83: -166393 | N83: -199154 | O83: 9287 | P83: 4633 | Q83: 169643 | R83: 16881 | S83: 10055 | T83: 44819 | U83: 77610 | V83: 2559 | W83: 0 | X83: 0
B85: Selisih Kumulatif | H85: 80000 | J85: 127870 | K85: 127870 | L85: 120062 | M85: -46331 | N85: -245485 | O85: -236198 | P85: -231565 | Q85: -61922 | R85: -45041 | S85: -34986 | T85: 9833 | U85: 87443 | V85: 90002 | W85: 90002 | X85: 90002
B86: Selisih Kumulatif Borrowing HO yang di Rollover | J86: 127870 | K86: 127870 | L86: 120062
J87: 37870 | K87: 0 | L87: -7808
B88: *) | C88: Pada rentan waktu 1 bulan terdapat pinjaman dari HO / KCLN Lain yang jatuh tempo, yaitu
C89: Up to 1 Wk | G89: 0
C90: > 1 Wk to 2 Wk | G90: 0 | H90: 0
C91: >2 WK to 1 Month | G91: 0
B92: Apabila pinjaman dari HO dikeluarkan maka Selisih Kumulatif sampai dengan 1 bulan adalah USD 120,062
B93: Sudah mendapat persetujuan dari HO untuk dilakukan R/O
C95: *) | D95: Angka-angka berdasarkan jatuh tempo sesuai dengan kontrak untuk yang memiliki jatuh tempo kontraktual dan/atau estimasi dengan menggunakan berbagai asumsi untuk yang tidak memiliki jatuh tempo kontraktual | U95: PT Bank Negara Indonesia (Persero) Tbk.
C96: **) | D96: Termasuk Surat Berharga yang dijual dengan janji dibeli kembali (Repo)
C97: ***) | D97: Diisi berdasarkan perkiraan diperoleh pembayaran atas kredit yang berdasarkan kontrak sudah jatuh tempo
C98: ****) | D98: Termasuk yang diperhitungkan dalam KPMM dan dilaporkan di LBU pada pos Modal Pinjaman
C99: *****) | D99: Yang diperkirakan akan mempengaruhi arus kas (menjadi tagihan)
C100: ******) | D100: Yang diperkirakan akan mempengaruhi arus kas (menjadi kewajiban)
C102: catatan: Core Giro non bank berdasarkan data historis selama Dua (2) tahun.
B104: Catatan:
B105: ¨ | C105: Pos-pos dalam maturity profile diisi sesuai pembukuan Bank Pelapor berdasarkan sisa waktu sampai dengan jatuh tempo sesuai kontrak untuk pos neraca dan rekening administratif yang memiliki jatuh tempo kontraktual dan/ atau asumsi utk pos neraca dan rekening administratif yang tidak memiliki jatuh tempo kontraktual (non maturity items)
B109: ¨ | C109: Yang dimasukkan dalam pos-pos neraca adalah hanya pos-pos dengan karakteristik memiliki arus kas masuk / atau arus kas keluar, sehingga tidak seluruh pos di neraca di masukkan dalam laporan ini. Contoh pos neraca yang tidak dimasukkan dalam laporan ini antara lain asset tetap, AYDA, properti terbengkalai, penyertaan, dan modal
B114: ¨ | C114: Sebagai kontrol, agar sesuai dengan neraca (balance antara asset & liability --> Total Asset - Total Liability = 0 di kolom saldo (H)), maka pos-pos yang tidak dimasukkan ke dalam maturity profile tetap dimasukkan ke pos poin 7. Lainnya diletakkan di kolom (P).
C125: Tagihan --> Buy
C126: Kewajiban --> Sell | Y126: 0 | Z126: 0 | AA126: 0 | AB126: 0 | AC126: 0 | AD126: 0 | AE126: 0 | AF126: 0 | AG126: 0 | AH126: 0 | AI126: 0
Y127: 0 | Z127: 0 | AA127: 0 | AB127: 0 | AC127: 0 | AD127: 0 | AE127: 0 | AF127: 0 | AG127: 0 | AH127: 0 | AI127: 0
H129: 399900.84
